[
  {
    "id": 15349,
    "game_id": "401856478",
    "prediction_date": "2026-03-19T12:36:05.682125",
    "home_win_prob": 0.9900000095367432,
    "away_win_prob": 0.009999999776482582,
    "predicted_winner": "Duke",
    "predicted_home_win": 1,
    "confidence": 0.8500000238418579,
    "model_name": "AdaptivePredictor",
    "model_version": "25c5331",
    "config_version": "7dd58a0bb0e2",
    "commit_hash": "3fcec26",
    "source": "live",
    "created_at": "2026-03-12T12:34:39.960277",
    "explanation": "Duke is strongly favored: they are significantly stronger overall, they have a major offensive advantage, and they have a vastly superior defense.",
    "game_date": "2026-03-19T00:00:00",
    "home_team": "Duke",
    "away_team": "Siena Saints",
    "home_moneyline": -20000,
    "away_moneyline": 3500
  },
  {
    "id": 15334,
    "game_id": "401856493",
    "prediction_date": "2026-03-19T12:36:05.682675",
    "home_win_prob": 0.9900000095367432,
    "away_win_prob": 0.009999999776482582,
    "predicted_winner": "Houston",
    "predicted_home_win": 1,
    "confidence": 0.8500000238418579,
    "model_name": "AdaptivePredictor",
    "model_version": "25c5331",
    "config_version": "7dd58a0bb0e2",
    "commit_hash": "3fcec26",
    "source": "live",
    "created_at": "2026-03-12T12:34:39.912306",
    "explanation": "Houston is strongly favored: they are significantly stronger overall, they have a major offensive advantage, and they have a vastly superior defense.",
    "game_date": "2026-03-19T00:00:00",
    "home_team": "Houston",
    "away_team": "Idaho",
    "home_moneyline": -8000,
    "away_moneyline": 2200
  },
  {
    "id": 15342,
    "game_id": "401856485",
    "prediction_date": "2026-03-19T12:36:05.682628",
    "home_win_prob": 0.9900000095367432,
    "away_win_prob": 0.009999999776482582,
    "predicted_winner": "Gonzaga",
    "predicted_home_win": 1,
    "confidence": 0.8500000238418579,
    "model_name": "AdaptivePredictor",
    "model_version": "25c5331",
    "config_version": "7dd58a0bb0e2",
    "commit_hash": "3fcec26",
    "source": "live",
    "created_at": "2026-03-12T12:34:39.937732",
    "explanation": "Gonzaga is strongly favored: they are significantly stronger overall, they have a major offensive advantage, and they have a vastly superior defense.",
    "game_date": "2026-03-19T00:00:00",
    "home_team": "Gonzaga",
    "away_team": "Kennesaw State",
    "home_moneyline": -4000,
    "away_moneyline": 1600
  },
  {
    "id": 15336,
    "game_id": "401856491",
    "prediction_date": "2026-03-19T12:36:05.682526",
    "home_win_prob": 0.9900000095367432,
    "away_win_prob": 0.009999999776482582,
    "predicted_winner": "Illinois",
    "predicted_home_win": 1,
    "confidence": 0.8500000238418579,
    "model_name": "AdaptivePredictor",
    "model_version": "25c5331",
    "config_version": "7dd58a0bb0e2",
    "commit_hash": "3fcec26",
    "source": "live",
    "created_at": "2026-03-12T12:34:39.918690",
    "explanation": "Illinois is strongly favored: they are significantly stronger overall, they have a major offensive advantage, and they have a vastly superior defense.",
    "game_date": "2026-03-19T00:00:00",
    "home_team": "Illinois Fighting",
    "away_team": "Pennsylvania",
    "home_moneyline": -8000,
    "away_moneyline": 2200
  },
  {
    "id": 15364,
    "game_id": "401856495",
    "prediction_date": "2026-03-19T12:36:05.683314",
    "home_win_prob": 0.9900000095367432,
    "away_win_prob": 0.009999999776482582,
    "predicted_winner": "Kansas",
    "predicted_home_win": 1,
    "confidence": 0.8500000238418579,
    "model_name": "AdaptivePredictor",
    "model_version": "25c5331",
    "config_version": "7dd58a0bb0e2",
    "commit_hash": "3fcec26",
    "source": "live",
    "created_at": "2026-03-13T12:34:40.526244",
    "explanation": "Kansas is strongly favored: they are significantly stronger overall, they have a major offensive advantage, and they have a vastly superior defense.",
    "game_date": "2026-03-20T00:00:00",
    "home_team": "Kansas",
    "away_team": "California Baptist",
    "home_moneyline": -1200,
    "away_moneyline": 750
  },
  {
    "id": 15350,
    "game_id": "401856529",
    "prediction_date": "2026-03-19T12:36:05.682814",
    "home_win_prob": 0.9900000095367432,
    "away_win_prob": 0.009999999776482582,
    "predicted_winner": "Arizona",
    "predicted_home_win": 1,
    "confidence": 0.8500000238418579,
    "model_name": "AdaptivePredictor",
    "model_version": "25c5331",
    "config_version": "7dd58a0bb0e2",
    "commit_hash": "3fcec26",
    "source": "live",
    "created_at": "2026-03-13T12:34:40.483895",
    "explanation": "Arizona is strongly favored: they are significantly stronger overall, they have a major offensive advantage, and they have a vastly superior defense.",
    "game_date": "2026-03-20T00:00:00",
    "home_team": "Arizona",
    "away_team": "Long Island University",
    "home_moneyline": -100000,
    "away_moneyline": 5000
  },
  {
    "id": 15355,
    "game_id": "401856524",
    "prediction_date": "2026-03-19T12:36:05.682905",
    "home_win_prob": 0.9900000095367432,
    "away_win_prob": 0.009999999776482582,
    "predicted_winner": "Iowa State",
    "predicted_home_win": 1,
    "confidence": 0.8500000238418579,
    "model_name": "AdaptivePredictor",
    "model_version": "25c5331",
    "config_version": "7dd58a0bb0e2",
    "commit_hash": "3fcec26",
    "source": "live",
    "created_at": "2026-03-13T12:34:40.498938",
    "explanation": "Iowa State is strongly favored: they are significantly stronger overall, they have a major offensive advantage, and they have a vastly superior defense.",
    "game_date": "2026-03-20T00:00:00",
    "home_team": "Iowa State",
    "away_team": "Tennessee State",
    "home_moneyline": -8000,
    "away_moneyline": 2200
  },
  {
    "id": 15356,
    "game_id": "401856523",
    "prediction_date": "2026-03-19T12:36:05.683270",
    "home_win_prob": 0.9900000095367432,
    "away_win_prob": 0.009999999776482582,
    "predicted_winner": "Florida",
    "predicted_home_win": 1,
    "confidence": 0.8500000238418579,
    "model_name": "AdaptivePredictor",
    "model_version": "25c5331",
    "config_version": "7dd58a0bb0e2",
    "commit_hash": "3fcec26",
    "source": "live",
    "created_at": "2026-03-13T12:34:40.501921",
    "explanation": "Florida is strongly favored: they are significantly stronger overall, they have a major offensive advantage, and they have a vastly superior defense.",
    "game_date": "2026-03-20T00:00:00",
    "home_team": "Florida",
    "away_team": "Prairie View A&M",
    "home_moneyline": -100000,
    "away_moneyline": 5000
  },
  {
    "id": 15340,
    "game_id": "401856487",
    "prediction_date": "2026-03-19T12:36:05.682580",
    "home_win_prob": 0.16987325251102448,
    "away_win_prob": 0.8301267623901367,
    "predicted_winner": "Saint Louis",
    "predicted_home_win": 0,
    "confidence": 0.8301267623901367,
    "model_name": "AdaptivePredictor",
    "model_version": "25c5331",
    "config_version": "7dd58a0bb0e2",
    "commit_hash": "3fcec26",
    "source": "live",
    "created_at": "2026-03-12T12:34:39.931515",
    "explanation": "Saint Louis is confidently favored: they are significantly stronger overall, they have faced much tougher competition, and they have a major offensive advantage.",
    "game_date": "2026-03-19T00:00:00",
    "home_team": "Georgia",
    "away_team": "Saint Louis",
    "home_moneyline": -148,
    "away_moneyline": 124
  },
  {
    "id": 15362,
    "game_id": "401856497",
    "prediction_date": "2026-03-19T12:36:05.683359",
    "home_win_prob": 0.8150727152824402,
    "away_win_prob": 0.18492725491523743,
    "predicted_winner": "UConn",
    "predicted_home_win": 1,
    "confidence": 0.8150727152824402,
    "model_name": "AdaptivePredictor",
    "model_version": "25c5331",
    "config_version": "7dd58a0bb0e2",
    "commit_hash": "3fcec26",
    "source": "live",
    "created_at": "2026-03-13T12:34:40.520071",
    "explanation": "UConn is confidently favored: they are significantly stronger overall, they have a major offensive advantage, and they have a vastly superior defense.",
    "game_date": "2026-03-20T00:00:00",
    "home_team": "UConn",
    "away_team": "Furman",
    "home_moneyline": -4500,
    "away_moneyline": 1700
  },
  {
    "id": 15365,
    "game_id": "401856494",
    "prediction_date": "2026-03-19T12:36:05.683133",
    "home_win_prob": 0.8150727152824402,
    "away_win_prob": 0.18492725491523743,
    "predicted_winner": "St. John's",
    "predicted_home_win": 1,
    "confidence": 0.8150727152824402,
    "model_name": "AdaptivePredictor",
    "model_version": "25c5331",
    "config_version": "7dd58a0bb0e2",
    "commit_hash": "3fcec26",
    "source": "live",
    "created_at": "2026-03-13T12:34:40.529214",
    "explanation": "St. John's is confidently favored: they are significantly stronger overall, they have a major offensive advantage, and they have a vastly superior defense.",
    "game_date": "2026-03-20T00:00:00",
    "home_team": "St. John's",
    "away_team": "Northern Iowa",
    "home_moneyline": -535,
    "away_moneyline": 400
  },
  {
    "id": 15344,
    "game_id": "401856483",
    "prediction_date": "2026-03-19T12:36:05.682222",
    "home_win_prob": 0.785036563873291,
    "away_win_prob": 0.21496343612670898,
    "predicted_winner": "Michigan State",
    "predicted_home_win": 1,
    "confidence": 0.785036563873291,
    "model_name": "AdaptivePredictor",
    "model_version": "25c5331",
    "config_version": "7dd58a0bb0e2",
    "commit_hash": "3fcec26",
    "source": "live",
    "created_at": "2026-03-12T12:34:39.943818",
    "explanation": "Michigan State is confidently favored: they are significantly stronger overall, they have a major offensive advantage, and they have a vastly superior defense.",
    "game_date": "2026-03-19T00:00:00",
    "home_team": "Michigan State",
    "away_team": "North Dakota State",
    "home_moneyline": -1800,
    "away_moneyline": 1000
  },
  {
    "id": 15346,
    "game_id": "401856481",
    "prediction_date": "2026-03-19T12:36:05.682269",
    "home_win_prob": 0.785036563873291,
    "away_win_prob": 0.21496343612670898,
    "predicted_winner": "Arkansas",
    "predicted_home_win": 1,
    "confidence": 0.785036563873291,
    "model_name": "AdaptivePredictor",
    "model_version": "25c5331",
    "config_version": "7dd58a0bb0e2",
    "commit_hash": "3fcec26",
    "source": "live",
    "created_at": "2026-03-12T12:34:39.950172",
    "explanation": "Arkansas is confidently favored: they are significantly stronger overall, they have a major offensive advantage, and they have a vastly superior defense.",
    "game_date": "2026-03-19T00:00:00",
    "home_team": "Arkansas",
    "away_team": "Hawai'i Rainbow",
    "home_moneyline": -1450,
    "away_moneyline": 850
  },
  {
    "id": 15341,
    "game_id": "401856486",
    "prediction_date": "2026-03-19T12:36:05.682365",
    "home_win_prob": 0.785036563873291,
    "away_win_prob": 0.21496343612670898,
    "predicted_winner": "Michigan",
    "predicted_home_win": 1,
    "confidence": 0.785036563873291,
    "model_name": "AdaptivePredictor",
    "model_version": "25c5331",
    "config_version": "7dd58a0bb0e2",
    "commit_hash": "3fcec26",
    "source": "live",
    "created_at": "2026-03-12T12:34:39.934606",
    "explanation": "Michigan is confidently favored: they are significantly stronger overall, they have a major offensive advantage, and they have a vastly superior defense.",
    "game_date": "2026-03-19T00:00:00",
    "home_team": "Michigan",
    "away_team": "Howard",
    "home_moneyline": -20000,
    "away_moneyline": 3500
  },
  {
    "id": 15347,
    "game_id": "401856480",
    "prediction_date": "2026-03-19T12:36:05.682075",
    "home_win_prob": 0.785036563873291,
    "away_win_prob": 0.21496343612670898,
    "predicted_winner": "Wisconsin",
    "predicted_home_win": 1,
    "confidence": 0.785036563873291,
    "model_name": "AdaptivePredictor",
    "model_version": "25c5331",
    "config_version": "7dd58a0bb0e2",
    "commit_hash": "3fcec26",
    "source": "live",
    "created_at": "2026-03-12T12:34:39.953299",
    "explanation": "Wisconsin is confidently favored: they are significantly stronger overall, they have a major offensive advantage, and they have a vastly superior defense.",
    "game_date": "2026-03-19T00:00:00",
    "home_team": "Wisconsin",
    "away_team": "High Point",
    "home_moneyline": -485,
    "away_moneyline": 370
  },
  {
    "id": 15338,
    "game_id": "401856489",
    "prediction_date": "2026-03-19T12:36:05.681965",
    "home_win_prob": 0.785036563873291,
    "away_win_prob": 0.21496343612670898,
    "predicted_winner": "Nebraska Cornhuskers",
    "predicted_home_win": 1,
    "confidence": 0.785036563873291,
    "model_name": "AdaptivePredictor",
    "model_version": "25c5331",
    "config_version": "7dd58a0bb0e2",
    "commit_hash": "3fcec26",
    "source": "live",
    "created_at": "2026-03-12T12:34:39.925039",
    "explanation": "Nebraska Cornhuskers is confidently favored: they are significantly stronger overall, they have a major offensive advantage, and they have a vastly superior defense.",
    "game_date": "2026-03-19T00:00:00",
    "home_team": "Nebraska Cornhuskers",
    "away_team": "Troy",
    "home_moneyline": -1000,
    "away_moneyline": 650
  },
  {
    "id": 15353,
    "game_id": "401856526",
    "prediction_date": "2026-03-19T12:36:05.682859",
    "home_win_prob": 0.785036563873291,
    "away_win_prob": 0.21496343612670898,
    "predicted_winner": "Virginia",
    "predicted_home_win": 1,
    "confidence": 0.785036563873291,
    "model_name": "AdaptivePredictor",
    "model_version": "25c5331",
    "config_version": "7dd58a0bb0e2",
    "commit_hash": "3fcec26",
    "source": "live",
    "created_at": "2026-03-13T12:34:40.492933",
    "explanation": "Virginia is confidently favored: they are significantly stronger overall, they have a major offensive advantage, and they have a vastly superior defense.",
    "game_date": "2026-03-20T00:00:00",
    "home_team": "Virginia",
    "away_team": "Wright State",
    "home_moneyline": -2800,
    "away_moneyline": 1300
  },
  {
    "id": 15358,
    "game_id": "401856521",
    "prediction_date": "2026-03-19T12:36:05.682950",
    "home_win_prob": 0.785036563873291,
    "away_win_prob": 0.21496343612670898,
    "predicted_winner": "Alabama Crimson Tide",
    "predicted_home_win": 1,
    "confidence": 0.785036563873291,
    "model_name": "AdaptivePredictor",
    "model_version": "25c5331",
    "config_version": "7dd58a0bb0e2",
    "commit_hash": "3fcec26",
    "source": "live",
    "created_at": "2026-03-13T12:34:40.507986",
    "explanation": "Alabama Crimson Tide is confidently favored: they are significantly stronger overall, they have a major offensive advantage, and they have a vastly superior defense.",
    "game_date": "2026-03-20T00:00:00",
    "home_team": "Alabama Crimson Tide",
    "away_team": "Hofstra Pride",
    "home_moneyline": -800,
    "away_moneyline": 550
  },
  {
    "id": 15357,
    "game_id": "401856522",
    "prediction_date": "2026-03-19T12:36:05.683087",
    "home_win_prob": 0.785036563873291,
    "away_win_prob": 0.21496343612670898,
    "predicted_winner": "Clemson",
    "predicted_home_win": 1,
    "confidence": 0.785036563873291,
    "model_name": "AdaptivePredictor",
    "model_version": "25c5331",
    "config_version": "7dd58a0bb0e2",
    "commit_hash": "3fcec26",
    "source": "live",
    "created_at": "2026-03-13T12:34:40.504959",
    "explanation": "Clemson is confidently favored: they are dominant at their home venue, they are significantly stronger overall, and they have a vastly superior defense.",
    "game_date": "2026-03-20T00:00:00",
    "home_team": "Clemson",
    "away_team": "Iowa",
    "home_moneyline": 114,
    "away_moneyline": -135
  },
  {
    "id": 15360,
    "game_id": "401856519",
    "prediction_date": "2026-03-19T12:36:05.683225",
    "home_win_prob": 0.785036563873291,
    "away_win_prob": 0.21496343612670898,
    "predicted_winner": "Purdue",
    "predicted_home_win": 1,
    "confidence": 0.785036563873291,
    "model_name": "AdaptivePredictor",
    "model_version": "25c5331",
    "config_version": "7dd58a0bb0e2",
    "commit_hash": "3fcec26",
    "source": "live",
    "created_at": "2026-03-13T12:34:40.514075",
    "explanation": "Purdue is confidently favored: they are significantly stronger overall, they have a major offensive advantage, and they have a vastly superior defense.",
    "game_date": "2026-03-20T00:00:00",
    "home_team": "Purdue",
    "away_team": "Queens University",
    "home_moneyline": -8000,
    "away_moneyline": 2200
  },
  {
    "id": 15339,
    "game_id": "401856488",
    "prediction_date": "2026-03-19T12:36:05.682174",
    "home_win_prob": 0.676749587059021,
    "away_win_prob": 0.3232504427433014,
    "predicted_winner": "Vanderbilt",
    "predicted_home_win": 1,
    "confidence": 0.676749587059021,
    "model_name": "AdaptivePredictor",
    "model_version": "25c5331",
    "config_version": "7dd58a0bb0e2",
    "commit_hash": "3fcec26",
    "source": "live",
    "created_at": "2026-03-12T12:34:39.928301",
    "explanation": "Vanderbilt is favored: they are significantly stronger overall, they have a major offensive advantage, and they have a vastly superior defense.",
    "game_date": "2026-03-19T00:00:00",
    "home_team": "Vanderbilt",
    "away_team": "McNeese",
    "home_moneyline": -750,
    "away_moneyline": 525
  },
  {
    "id": 15337,
    "game_id": "401856490",
    "prediction_date": "2026-03-19T12:36:05.682317",
    "home_win_prob": 0.6230432391166687,
    "away_win_prob": 0.3769567608833313,
    "predicted_winner": "North Carolina",
    "predicted_home_win": 1,
    "confidence": 0.6230432391166687,
    "model_name": "AdaptivePredictor",
    "model_version": "25c5331",
    "config_version": "7dd58a0bb0e2",
    "commit_hash": "3fcec26",
    "source": "live",
    "created_at": "2026-03-12T12:34:39.921639",
    "explanation": "North Carolina is narrowly favored: they are significantly stronger overall, they have a major offensive advantage, and they have a vastly superior defense.",
    "game_date": "2026-03-19T00:00:00",
    "home_team": "North Carolina",
    "away_team": "VCU",
    "home_moneyline": -148,
    "away_moneyline": 124
  },
  {
    "id": 15359,
    "game_id": "401856520",
    "prediction_date": "2026-03-19T12:36:05.682767",
    "home_win_prob": 0.6230432391166687,
    "away_win_prob": 0.3769567608833313,
    "predicted_winner": "Texas Tech",
    "predicted_home_win": 1,
    "confidence": 0.6230432391166687,
    "model_name": "AdaptivePredictor",
    "model_version": "25c5331",
    "config_version": "7dd58a0bb0e2",
    "commit_hash": "3fcec26",
    "source": "live",
    "created_at": "2026-03-13T12:34:40.511106",
    "explanation": "Texas Tech is narrowly favored: they are significantly stronger overall, they have a major offensive advantage, and they have a vastly superior defense.",
    "game_date": "2026-03-20T00:00:00",
    "home_team": "Texas Tech",
    "away_team": "Akron",
    "home_moneyline": -325,
    "away_moneyline": 260
  },
  {
    "id": 15363,
    "game_id": "401856496",
    "prediction_date": "2026-03-19T12:36:05.683180",
    "home_win_prob": 0.6230432391166687,
    "away_win_prob": 0.3769567608833313,
    "predicted_winner": "UCLA",
    "predicted_home_win": 1,
    "confidence": 0.6230432391166687,
    "model_name": "AdaptivePredictor",
    "model_version": "25c5331",
    "config_version": "7dd58a0bb0e2",
    "commit_hash": "3fcec26",
    "source": "live",
    "created_at": "2026-03-13T12:34:40.523232",
    "explanation": "UCLA is narrowly favored: they are significantly stronger overall, they have a major offensive advantage, and they have a vastly superior defense.",
    "game_date": "2026-03-20T00:00:00",
    "home_team": "UCLA",
    "away_team": "UCF",
    "home_moneyline": -245,
    "away_moneyline": 200
  },
  {
    "id": 15348,
    "game_id": "401856479",
    "prediction_date": "2026-03-19T12:36:05.681891",
    "home_win_prob": 0.39262813329696655,
    "away_win_prob": 0.6073718667030334,
    "predicted_winner": "TCU Horned Frogs",
    "predicted_home_win": 0,
    "confidence": 0.6073718667030334,
    "model_name": "AdaptivePredictor",
    "model_version": "25c5331",
    "config_version": "7dd58a0bb0e2",
    "commit_hash": "3fcec26",
    "source": "live",
    "created_at": "2026-03-12T12:34:39.957146",
    "explanation": "TCU Horned Frogs is narrowly favored: they are significantly stronger overall, they have faced much tougher competition, and they have a major offensive advantage.",
    "game_date": "2026-03-19T00:00:00",
    "home_team": "Ohio State",
    "away_team": "TCU Horned Frogs",
    "home_moneyline": -155,
    "away_moneyline": 130
  },
  {
    "id": 15345,
    "game_id": "401856482",
    "prediction_date": "2026-03-19T12:36:05.682022",
    "home_win_prob": 0.39262813329696655,
    "away_win_prob": 0.6073718667030334,
    "predicted_winner": "South Florida",
    "predicted_home_win": 0,
    "confidence": 0.6073718667030334,
    "model_name": "AdaptivePredictor",
    "model_version": "25c5331",
    "config_version": "7dd58a0bb0e2",
    "commit_hash": "3fcec26",
    "source": "live",
    "created_at": "2026-03-12T12:34:39.947071",
    "explanation": "South Florida is narrowly favored: they are significantly stronger overall, they have a major offensive advantage, and they have a vastly superior defense.",
    "game_date": "2026-03-19T00:00:00",
    "home_team": "Louisville",
    "away_team": "South Florida",
    "home_moneyline": -198,
    "away_moneyline": 164
  },
  {
    "id": 15354,
    "game_id": "401856525",
    "prediction_date": "2026-03-19T12:36:05.682721",
    "home_win_prob": 0.39262813329696655,
    "away_win_prob": 0.6073718667030334,
    "predicted_winner": "Santa Clara",
    "predicted_home_win": 0,
    "confidence": 0.6073718667030334,
    "model_name": "AdaptivePredictor",
    "model_version": "25c5331",
    "config_version": "7dd58a0bb0e2",
    "commit_hash": "3fcec26",
    "source": "live",
    "created_at": "2026-03-13T12:34:40.495888",
    "explanation": "Santa Clara is narrowly favored: they are significantly stronger overall, they have a major offensive advantage, and they have a vastly superior defense.",
    "game_date": "2026-03-20T00:00:00",
    "home_team": "Kentucky",
    "away_team": "Santa Clara",
    "home_moneyline": -162,
    "away_moneyline": 136
  },
  {
    "id": 15351,
    "game_id": "401856528",
    "prediction_date": "2026-03-19T12:36:05.682996",
    "home_win_prob": 0.39262813329696655,
    "away_win_prob": 0.6073718667030334,
    "predicted_winner": "Utah State",
    "predicted_home_win": 0,
    "confidence": 0.6073718667030334,
    "model_name": "AdaptivePredictor",
    "model_version": "25c5331",
    "config_version": "7dd58a0bb0e2",
    "commit_hash": "3fcec26",
    "source": "live",
    "created_at": "2026-03-13T12:34:40.487050",
    "explanation": "Utah State is narrowly favored: they are significantly stronger overall, they have faced much tougher competition, and they have a major offensive advantage.",
    "game_date": "2026-03-20T00:00:00",
    "home_team": "Villanova",
    "away_team": "Utah State",
    "home_moneyline": 105,
    "away_moneyline": -125
  },
  {
    "id": 15370,
    "game_id": "401856537",
    "prediction_date": "2026-03-19T12:36:05.683448",
    "home_win_prob": 0.39262813329696655,
    "away_win_prob": 0.6073718667030334,
    "predicted_winner": "TBD",
    "predicted_home_win": 0,
    "confidence": 0.6073718667030334,
    "model_name": "AdaptivePredictor",
    "model_version": "25c5331",
    "config_version": "7dd58a0bb0e2",
    "commit_hash": "3fcec26",
    "source": "live",
    "created_at": "2026-03-15T12:32:22.797496",
    "explanation": "TBD is narrowly favored: they are dominant at their home venue and they have a solid home record.",
    "game_date": "2026-03-21T00:00:00",
    "home_team": "TBD",
    "away_team": "TBD",
    "home_moneyline": null,
    "away_moneyline": null
  },
  {
    "id": 15374,
    "game_id": "401858352",
    "prediction_date": "2026-03-19T12:36:05.683839",
    "home_win_prob": 0.39262813329696655,
    "away_win_prob": 0.6073718667030334,
    "predicted_winner": "TBD",
    "predicted_home_win": 0,
    "confidence": 0.6073718667030334,
    "model_name": "AdaptivePredictor",
    "model_version": "25c5331",
    "config_version": "7dd58a0bb0e2",
    "commit_hash": "3fcec26",
    "source": "live",
    "created_at": "2026-03-15T12:32:22.809864",
    "explanation": "TBD is narrowly favored: they are dominant at their home venue and they have a solid home record.",
    "game_date": "2026-03-21T00:00:00",
    "home_team": "TBD",
    "away_team": "TBD",
    "home_moneyline": null,
    "away_moneyline": null
  },
  {
    "id": 15377,
    "game_id": "401858349",
    "prediction_date": "2026-03-19T12:36:05.683973",
    "home_win_prob": 0.39262813329696655,
    "away_win_prob": 0.6073718667030334,
    "predicted_winner": "TBD",
    "predicted_home_win": 0,
    "confidence": 0.6073718667030334,
    "model_name": "AdaptivePredictor",
    "model_version": "25c5331",
    "config_version": "7dd58a0bb0e2",
    "commit_hash": "3fcec26",
    "source": "live",
    "created_at": "2026-03-15T12:32:22.819075",
    "explanation": "TBD is narrowly favored: they are dominant at their home venue and they have a solid home record.",
    "game_date": "2026-03-21T00:00:00",
    "home_team": "TBD",
    "away_team": "TBD",
    "home_moneyline": null,
    "away_moneyline": null
  },
  {
    "id": 15376,
    "game_id": "401858350",
    "prediction_date": "2026-03-19T12:36:05.683928",
    "home_win_prob": 0.39262813329696655,
    "away_win_prob": 0.6073718667030334,
    "predicted_winner": "TBD",
    "predicted_home_win": 0,
    "confidence": 0.6073718667030334,
    "model_name": "AdaptivePredictor",
    "model_version": "25c5331",
    "config_version": "7dd58a0bb0e2",
    "commit_hash": "3fcec26",
    "source": "live",
    "created_at": "2026-03-15T12:32:22.816026",
    "explanation": "TBD is narrowly favored: they are dominant at their home venue and they have a solid home record.",
    "game_date": "2026-03-21T00:00:00",
    "home_team": "TBD",
    "away_team": "TBD",
    "home_moneyline": null,
    "away_moneyline": null
  },
  {
    "id": 15375,
    "game_id": "401858351",
    "prediction_date": "2026-03-19T12:36:05.683884",
    "home_win_prob": 0.39262813329696655,
    "away_win_prob": 0.6073718667030334,
    "predicted_winner": "TBD",
    "predicted_home_win": 0,
    "confidence": 0.6073718667030334,
    "model_name": "AdaptivePredictor",
    "model_version": "25c5331",
    "config_version": "7dd58a0bb0e2",
    "commit_hash": "3fcec26",
    "source": "live",
    "created_at": "2026-03-15T12:32:22.812960",
    "explanation": "TBD is narrowly favored: they are dominant at their home venue and they have a solid home record.",
    "game_date": "2026-03-21T00:00:00",
    "home_team": "TBD",
    "away_team": "TBD",
    "home_moneyline": null,
    "away_moneyline": null
  },
  {
    "id": 15367,
    "game_id": "401856536",
    "prediction_date": "2026-03-19T12:36:05.683492",
    "home_win_prob": 0.39262813329696655,
    "away_win_prob": 0.6073718667030334,
    "predicted_winner": "TBD",
    "predicted_home_win": 0,
    "confidence": 0.6073718667030334,
    "model_name": "AdaptivePredictor",
    "model_version": "25c5331",
    "config_version": "7dd58a0bb0e2",
    "commit_hash": "3fcec26",
    "source": "live",
    "created_at": "2026-03-15T12:32:22.787995",
    "explanation": "TBD is narrowly favored: they are dominant at their home venue and they have a solid home record.",
    "game_date": "2026-03-21T00:00:00",
    "home_team": "TBD",
    "away_team": "TBD",
    "home_moneyline": null,
    "away_moneyline": null
  },
  {
    "id": 15368,
    "game_id": "401856535",
    "prediction_date": "2026-03-19T12:36:05.683564",
    "home_win_prob": 0.39262813329696655,
    "away_win_prob": 0.6073718667030334,
    "predicted_winner": "TBD",
    "predicted_home_win": 0,
    "confidence": 0.6073718667030334,
    "model_name": "AdaptivePredictor",
    "model_version": "25c5331",
    "config_version": "7dd58a0bb0e2",
    "commit_hash": "3fcec26",
    "source": "live",
    "created_at": "2026-03-15T12:32:22.791250",
    "explanation": "TBD is narrowly favored: they are dominant at their home venue and they have a solid home record.",
    "game_date": "2026-03-21T00:00:00",
    "home_team": "TBD",
    "away_team": "TBD",
    "home_moneyline": null,
    "away_moneyline": null
  },
  {
    "id": 15369,
    "game_id": "401856534",
    "prediction_date": "2026-03-19T12:36:05.683613",
    "home_win_prob": 0.39262813329696655,
    "away_win_prob": 0.6073718667030334,
    "predicted_winner": "TBD",
    "predicted_home_win": 0,
    "confidence": 0.6073718667030334,
    "model_name": "AdaptivePredictor",
    "model_version": "25c5331",
    "config_version": "7dd58a0bb0e2",
    "commit_hash": "3fcec26",
    "source": "live",
    "created_at": "2026-03-15T12:32:22.794309",
    "explanation": "TBD is narrowly favored: they are dominant at their home venue and they have a solid home record.",
    "game_date": "2026-03-21T00:00:00",
    "home_team": "TBD",
    "away_team": "TBD",
    "home_moneyline": null,
    "away_moneyline": null
  },
  {
    "id": 15366,
    "game_id": "401856533",
    "prediction_date": "2026-03-19T12:36:05.683659",
    "home_win_prob": 0.39262813329696655,
    "away_win_prob": 0.6073718667030334,
    "predicted_winner": "TBD",
    "predicted_home_win": 0,
    "confidence": 0.6073718667030334,
    "model_name": "AdaptivePredictor",
    "model_version": "25c5331",
    "config_version": "7dd58a0bb0e2",
    "commit_hash": "3fcec26",
    "source": "live",
    "created_at": "2026-03-15T12:32:22.784562",
    "explanation": "TBD is narrowly favored: they are dominant at their home venue and they have a solid home record.",
    "game_date": "2026-03-21T00:00:00",
    "home_team": "TBD",
    "away_team": "TBD",
    "home_moneyline": null,
    "away_moneyline": null
  },
  {
    "id": 15371,
    "game_id": "401856532",
    "prediction_date": "2026-03-19T12:36:05.683704",
    "home_win_prob": 0.39262813329696655,
    "away_win_prob": 0.6073718667030334,
    "predicted_winner": "TBD",
    "predicted_home_win": 0,
    "confidence": 0.6073718667030334,
    "model_name": "AdaptivePredictor",
    "model_version": "25c5331",
    "config_version": "7dd58a0bb0e2",
    "commit_hash": "3fcec26",
    "source": "live",
    "created_at": "2026-03-15T12:32:22.800704",
    "explanation": "TBD is narrowly favored: they are dominant at their home venue and they have a solid home record.",
    "game_date": "2026-03-21T00:00:00",
    "home_team": "TBD",
    "away_team": "TBD",
    "home_moneyline": null,
    "away_moneyline": null
  },
  {
    "id": 15372,
    "game_id": "401856531",
    "prediction_date": "2026-03-19T12:36:05.683749",
    "home_win_prob": 0.39262813329696655,
    "away_win_prob": 0.6073718667030334,
    "predicted_winner": "TBD",
    "predicted_home_win": 0,
    "confidence": 0.6073718667030334,
    "model_name": "AdaptivePredictor",
    "model_version": "25c5331",
    "config_version": "7dd58a0bb0e2",
    "commit_hash": "3fcec26",
    "source": "live",
    "created_at": "2026-03-15T12:32:22.803736",
    "explanation": "TBD is narrowly favored: they are dominant at their home venue and they have a solid home record.",
    "game_date": "2026-03-21T00:00:00",
    "home_team": "TBD",
    "away_team": "TBD",
    "home_moneyline": null,
    "away_moneyline": null
  },
  {
    "id": 15373,
    "game_id": "401856530",
    "prediction_date": "2026-03-19T12:36:05.683794",
    "home_win_prob": 0.39262813329696655,
    "away_win_prob": 0.6073718667030334,
    "predicted_winner": "TBD",
    "predicted_home_win": 0,
    "confidence": 0.6073718667030334,
    "model_name": "AdaptivePredictor",
    "model_version": "25c5331",
    "config_version": "7dd58a0bb0e2",
    "commit_hash": "3fcec26",
    "source": "live",
    "created_at": "2026-03-15T12:32:22.806840",
    "explanation": "TBD is narrowly favored: they are dominant at their home venue and they have a solid home record.",
    "game_date": "2026-03-21T00:00:00",
    "home_team": "TBD",
    "away_team": "TBD",
    "home_moneyline": null,
    "away_moneyline": null
  },
  {
    "id": 15389,
    "game_id": "401858353",
    "prediction_date": "2026-03-19T12:36:05.684524",
    "home_win_prob": 0.39262813329696655,
    "away_win_prob": 0.6073718667030334,
    "predicted_winner": "TBD",
    "predicted_home_win": 0,
    "confidence": 0.6073718667030334,
    "model_name": "AdaptivePredictor",
    "model_version": "25c5331",
    "config_version": "7dd58a0bb0e2",
    "commit_hash": "3fcec26",
    "source": "live",
    "created_at": "2026-03-15T12:32:22.857418",
    "explanation": "TBD is narrowly favored: they are dominant at their home venue and they have a solid home record.",
    "game_date": "2026-03-22T00:00:00",
    "home_team": "TBD",
    "away_team": "TBD",
    "home_moneyline": null,
    "away_moneyline": null
  },
  {
    "id": 15378,
    "game_id": "401856565",
    "prediction_date": "2026-03-19T12:36:05.684017",
    "home_win_prob": 0.39262813329696655,
    "away_win_prob": 0.6073718667030334,
    "predicted_winner": "TBD",
    "predicted_home_win": 0,
    "confidence": 0.6073718667030334,
    "model_name": "AdaptivePredictor",
    "model_version": "25c5331",
    "config_version": "7dd58a0bb0e2",
    "commit_hash": "3fcec26",
    "source": "live",
    "created_at": "2026-03-15T12:32:22.822155",
    "explanation": "TBD is narrowly favored: they are dominant at their home venue and they have a solid home record.",
    "game_date": "2026-03-22T00:00:00",
    "home_team": "TBD",
    "away_team": "TBD",
    "home_moneyline": null,
    "away_moneyline": null
  },
  {
    "id": 15379,
    "game_id": "401856564",
    "prediction_date": "2026-03-19T12:36:05.684062",
    "home_win_prob": 0.39262813329696655,
    "away_win_prob": 0.6073718667030334,
    "predicted_winner": "TBD",
    "predicted_home_win": 0,
    "confidence": 0.6073718667030334,
    "model_name": "AdaptivePredictor",
    "model_version": "25c5331",
    "config_version": "7dd58a0bb0e2",
    "commit_hash": "3fcec26",
    "source": "live",
    "created_at": "2026-03-15T12:32:22.825256",
    "explanation": "TBD is narrowly favored: they are dominant at their home venue and they have a solid home record.",
    "game_date": "2026-03-22T00:00:00",
    "home_team": "TBD",
    "away_team": "TBD",
    "home_moneyline": null,
    "away_moneyline": null
  },
  {
    "id": 15380,
    "game_id": "401856563",
    "prediction_date": "2026-03-19T12:36:05.684106",
    "home_win_prob": 0.39262813329696655,
    "away_win_prob": 0.6073718667030334,
    "predicted_winner": "TBD",
    "predicted_home_win": 0,
    "confidence": 0.6073718667030334,
    "model_name": "AdaptivePredictor",
    "model_version": "25c5331",
    "config_version": "7dd58a0bb0e2",
    "commit_hash": "3fcec26",
    "source": "live",
    "created_at": "2026-03-15T12:32:22.828665",
    "explanation": "TBD is narrowly favored: they are dominant at their home venue and they have a solid home record.",
    "game_date": "2026-03-22T00:00:00",
    "home_team": "TBD",
    "away_team": "TBD",
    "home_moneyline": null,
    "away_moneyline": null
  },
  {
    "id": 15381,
    "game_id": "401856562",
    "prediction_date": "2026-03-19T12:36:05.684152",
    "home_win_prob": 0.39262813329696655,
    "away_win_prob": 0.6073718667030334,
    "predicted_winner": "TBD",
    "predicted_home_win": 0,
    "confidence": 0.6073718667030334,
    "model_name": "AdaptivePredictor",
    "model_version": "25c5331",
    "config_version": "7dd58a0bb0e2",
    "commit_hash": "3fcec26",
    "source": "live",
    "created_at": "2026-03-15T12:32:22.832046",
    "explanation": "TBD is narrowly favored: they are dominant at their home venue and they have a solid home record.",
    "game_date": "2026-03-22T00:00:00",
    "home_team": "TBD",
    "away_team": "TBD",
    "home_moneyline": null,
    "away_moneyline": null
  },
  {
    "id": 15382,
    "game_id": "401856561",
    "prediction_date": "2026-03-19T12:36:05.684196",
    "home_win_prob": 0.39262813329696655,
    "away_win_prob": 0.6073718667030334,
    "predicted_winner": "TBD",
    "predicted_home_win": 0,
    "confidence": 0.6073718667030334,
    "model_name": "AdaptivePredictor",
    "model_version": "25c5331",
    "config_version": "7dd58a0bb0e2",
    "commit_hash": "3fcec26",
    "source": "live",
    "created_at": "2026-03-15T12:32:22.835167",
    "explanation": "TBD is narrowly favored: they are dominant at their home venue and they have a solid home record.",
    "game_date": "2026-03-22T00:00:00",
    "home_team": "TBD",
    "away_team": "TBD",
    "home_moneyline": null,
    "away_moneyline": null
  },
  {
    "id": 15383,
    "game_id": "401856560",
    "prediction_date": "2026-03-19T12:36:05.684241",
    "home_win_prob": 0.39262813329696655,
    "away_win_prob": 0.6073718667030334,
    "predicted_winner": "TBD",
    "predicted_home_win": 0,
    "confidence": 0.6073718667030334,
    "model_name": "AdaptivePredictor",
    "model_version": "25c5331",
    "config_version": "7dd58a0bb0e2",
    "commit_hash": "3fcec26",
    "source": "live",
    "created_at": "2026-03-15T12:32:22.838173",
    "explanation": "TBD is narrowly favored: they are dominant at their home venue and they have a solid home record.",
    "game_date": "2026-03-22T00:00:00",
    "home_team": "TBD",
    "away_team": "TBD",
    "home_moneyline": null,
    "away_moneyline": null
  },
  {
    "id": 15384,
    "game_id": "401856559",
    "prediction_date": "2026-03-19T12:36:05.684285",
    "home_win_prob": 0.39262813329696655,
    "away_win_prob": 0.6073718667030334,
    "predicted_winner": "TBD",
    "predicted_home_win": 0,
    "confidence": 0.6073718667030334,
    "model_name": "AdaptivePredictor",
    "model_version": "25c5331",
    "config_version": "7dd58a0bb0e2",
    "commit_hash": "3fcec26",
    "source": "live",
    "created_at": "2026-03-15T12:32:22.841097",
    "explanation": "TBD is narrowly favored: they are dominant at their home venue and they have a solid home record.",
    "game_date": "2026-03-22T00:00:00",
    "home_team": "TBD",
    "away_team": "TBD",
    "home_moneyline": null,
    "away_moneyline": null
  },
  {
    "id": 15385,
    "game_id": "401856558",
    "prediction_date": "2026-03-19T12:36:05.684330",
    "home_win_prob": 0.39262813329696655,
    "away_win_prob": 0.6073718667030334,
    "predicted_winner": "TBD",
    "predicted_home_win": 0,
    "confidence": 0.6073718667030334,
    "model_name": "AdaptivePredictor",
    "model_version": "25c5331",
    "config_version": "7dd58a0bb0e2",
    "commit_hash": "3fcec26",
    "source": "live",
    "created_at": "2026-03-15T12:32:22.844052",
    "explanation": "TBD is narrowly favored: they are dominant at their home venue and they have a solid home record.",
    "game_date": "2026-03-22T00:00:00",
    "home_team": "TBD",
    "away_team": "TBD",
    "home_moneyline": null,
    "away_moneyline": null
  },
  {
    "id": 15386,
    "game_id": "401858356",
    "prediction_date": "2026-03-19T12:36:05.684374",
    "home_win_prob": 0.39262813329696655,
    "away_win_prob": 0.6073718667030334,
    "predicted_winner": "TBD",
    "predicted_home_win": 0,
    "confidence": 0.6073718667030334,
    "model_name": "AdaptivePredictor",
    "model_version": "25c5331",
    "config_version": "7dd58a0bb0e2",
    "commit_hash": "3fcec26",
    "source": "live",
    "created_at": "2026-03-15T12:32:22.848332",
    "explanation": "TBD is narrowly favored: they are dominant at their home venue and they have a solid home record.",
    "game_date": "2026-03-22T00:00:00",
    "home_team": "TBD",
    "away_team": "TBD",
    "home_moneyline": null,
    "away_moneyline": null
  },
  {
    "id": 15387,
    "game_id": "401858355",
    "prediction_date": "2026-03-19T12:36:05.684419",
    "home_win_prob": 0.39262813329696655,
    "away_win_prob": 0.6073718667030334,
    "predicted_winner": "TBD",
    "predicted_home_win": 0,
    "confidence": 0.6073718667030334,
    "model_name": "AdaptivePredictor",
    "model_version": "25c5331",
    "config_version": "7dd58a0bb0e2",
    "commit_hash": "3fcec26",
    "source": "live",
    "created_at": "2026-03-15T12:32:22.851318",
    "explanation": "TBD is narrowly favored: they are dominant at their home venue and they have a solid home record.",
    "game_date": "2026-03-22T00:00:00",
    "home_team": "TBD",
    "away_team": "TBD",
    "home_moneyline": null,
    "away_moneyline": null
  },
  {
    "id": 15388,
    "game_id": "401858354",
    "prediction_date": "2026-03-19T12:36:05.684463",
    "home_win_prob": 0.39262813329696655,
    "away_win_prob": 0.6073718667030334,
    "predicted_winner": "TBD",
    "predicted_home_win": 0,
    "confidence": 0.6073718667030334,
    "model_name": "AdaptivePredictor",
    "model_version": "25c5331",
    "config_version": "7dd58a0bb0e2",
    "commit_hash": "3fcec26",
    "source": "live",
    "created_at": "2026-03-15T12:32:22.854405",
    "explanation": "TBD is narrowly favored: they are dominant at their home venue and they have a solid home record.",
    "game_date": "2026-03-22T00:00:00",
    "home_team": "TBD",
    "away_team": "TBD",
    "home_moneyline": null,
    "away_moneyline": null
  },
  {
    "id": 15391,
    "game_id": "401858358",
    "prediction_date": "2026-03-19T12:36:05.684621",
    "home_win_prob": 0.39262813329696655,
    "away_win_prob": 0.6073718667030334,
    "predicted_winner": "TBD",
    "predicted_home_win": 0,
    "confidence": 0.6073718667030334,
    "model_name": "AdaptivePredictor",
    "model_version": "25c5331",
    "config_version": "7dd58a0bb0e2",
    "commit_hash": "3fcec26",
    "source": "live",
    "created_at": "2026-03-18T12:40:58.930357",
    "explanation": "TBD is narrowly favored: they are dominant at their home venue and they have a solid home record.",
    "game_date": "2026-03-24T00:00:00",
    "home_team": "TBD",
    "away_team": "TBD",
    "home_moneyline": null,
    "away_moneyline": null
  },
  {
    "id": 15390,
    "game_id": "401858357",
    "prediction_date": "2026-03-19T12:36:05.684575",
    "home_win_prob": 0.39262813329696655,
    "away_win_prob": 0.6073718667030334,
    "predicted_winner": "TBD",
    "predicted_home_win": 0,
    "confidence": 0.6073718667030334,
    "model_name": "AdaptivePredictor",
    "model_version": "25c5331",
    "config_version": "7dd58a0bb0e2",
    "commit_hash": "3fcec26",
    "source": "live",
    "created_at": "2026-03-18T12:40:58.927240",
    "explanation": "TBD is narrowly favored: they are dominant at their home venue and they have a solid home record.",
    "game_date": "2026-03-24T00:00:00",
    "home_team": "TBD",
    "away_team": "TBD",
    "home_moneyline": null,
    "away_moneyline": null
  },
  {
    "id": 15392,
    "game_id": "401858359",
    "prediction_date": "2026-03-19T12:36:05.684666",
    "home_win_prob": 0.39262813329696655,
    "away_win_prob": 0.6073718667030334,
    "predicted_winner": "TBD",
    "predicted_home_win": 0,
    "confidence": 0.6073718667030334,
    "model_name": "AdaptivePredictor",
    "model_version": "25c5331",
    "config_version": "7dd58a0bb0e2",
    "commit_hash": "3fcec26",
    "source": "live",
    "created_at": "2026-03-18T12:40:58.933431",
    "explanation": "TBD is narrowly favored: they are dominant at their home venue and they have a solid home record.",
    "game_date": "2026-03-25T00:00:00",
    "home_team": "TBD",
    "away_team": "TBD",
    "home_moneyline": null,
    "away_moneyline": null
  },
  {
    "id": 15393,
    "game_id": "401858360",
    "prediction_date": "2026-03-19T12:36:05.684709",
    "home_win_prob": 0.39262813329696655,
    "away_win_prob": 0.6073718667030334,
    "predicted_winner": "TBD",
    "predicted_home_win": 0,
    "confidence": 0.6073718667030334,
    "model_name": "AdaptivePredictor",
    "model_version": "25c5331",
    "config_version": "7dd58a0bb0e2",
    "commit_hash": "3fcec26",
    "source": "live",
    "created_at": "2026-03-18T12:40:58.936499",
    "explanation": "TBD is narrowly favored: they are dominant at their home venue and they have a solid home record.",
    "game_date": "2026-03-25T00:00:00",
    "home_team": "TBD",
    "away_team": "TBD",
    "home_moneyline": null,
    "away_moneyline": null
  },
  {
    "id": 15397,
    "game_id": "401856566",
    "prediction_date": "2026-03-19T12:36:05.684890",
    "home_win_prob": 0.39262813329696655,
    "away_win_prob": 0.6073718667030334,
    "predicted_winner": "TBD",
    "predicted_home_win": 0,
    "confidence": 0.6073718667030334,
    "model_name": "AdaptivePredictor",
    "model_version": "25c5331",
    "config_version": "7dd58a0bb0e2",
    "commit_hash": "3fcec26",
    "source": "live",
    "created_at": "2026-03-19T12:36:05.929711",
    "explanation": "TBD is narrowly favored: they are dominant at their home venue and they have a solid home record.",
    "game_date": "2026-03-26T00:00:00",
    "home_team": "TBD",
    "away_team": "TBD",
    "home_moneyline": null,
    "away_moneyline": null
  },
  {
    "id": 15394,
    "game_id": "401856569",
    "prediction_date": "2026-03-19T12:36:05.684757",
    "home_win_prob": 0.39262813329696655,
    "away_win_prob": 0.6073718667030334,
    "predicted_winner": "TBD",
    "predicted_home_win": 0,
    "confidence": 0.6073718667030334,
    "model_name": "AdaptivePredictor",
    "model_version": "25c5331",
    "config_version": "7dd58a0bb0e2",
    "commit_hash": "3fcec26",
    "source": "live",
    "created_at": "2026-03-19T12:36:05.920639",
    "explanation": "TBD is narrowly favored: they are dominant at their home venue and they have a solid home record.",
    "game_date": "2026-03-26T00:00:00",
    "home_team": "TBD",
    "away_team": "TBD",
    "home_moneyline": null,
    "away_moneyline": null
  },
  {
    "id": 15395,
    "game_id": "401856568",
    "prediction_date": "2026-03-19T12:36:05.684802",
    "home_win_prob": 0.39262813329696655,
    "away_win_prob": 0.6073718667030334,
    "predicted_winner": "TBD",
    "predicted_home_win": 0,
    "confidence": 0.6073718667030334,
    "model_name": "AdaptivePredictor",
    "model_version": "25c5331",
    "config_version": "7dd58a0bb0e2",
    "commit_hash": "3fcec26",
    "source": "live",
    "created_at": "2026-03-19T12:36:05.923691",
    "explanation": "TBD is narrowly favored: they are dominant at their home venue and they have a solid home record.",
    "game_date": "2026-03-26T00:00:00",
    "home_team": "TBD",
    "away_team": "TBD",
    "home_moneyline": null,
    "away_moneyline": null
  },
  {
    "id": 15396,
    "game_id": "401856567",
    "prediction_date": "2026-03-19T12:36:05.684846",
    "home_win_prob": 0.39262813329696655,
    "away_win_prob": 0.6073718667030334,
    "predicted_winner": "TBD",
    "predicted_home_win": 0,
    "confidence": 0.6073718667030334,
    "model_name": "AdaptivePredictor",
    "model_version": "25c5331",
    "config_version": "7dd58a0bb0e2",
    "commit_hash": "3fcec26",
    "source": "live",
    "created_at": "2026-03-19T12:36:05.926604",
    "explanation": "TBD is narrowly favored: they are dominant at their home venue and they have a solid home record.",
    "game_date": "2026-03-26T00:00:00",
    "home_team": "TBD",
    "away_team": "TBD",
    "home_moneyline": null,
    "away_moneyline": null
  },
  {
    "id": 15343,
    "game_id": "401856484",
    "prediction_date": "2026-03-19T12:36:05.682414",
    "home_win_prob": 0.4685108959674835,
    "away_win_prob": 0.5314890742301941,
    "predicted_winner": "Texas Longhorns",
    "predicted_home_win": 0,
    "confidence": 0.5314890742301941,
    "model_name": "AdaptivePredictor",
    "model_version": "25c5331",
    "config_version": "7dd58a0bb0e2",
    "commit_hash": "3fcec26",
    "source": "live",
    "created_at": "2026-03-12T12:34:39.940790",
    "explanation": "Texas Longhorns is narrowly favored: they are significantly stronger overall, they are dominant at their home venue, and they have a major offensive advantage.",
    "game_date": "2026-03-19T00:00:00",
    "home_team": "BYU",
    "away_team": "Texas Longhorns",
    "home_moneyline": -135,
    "away_moneyline": 114
  },
  {
    "id": 15335,
    "game_id": "401856492",
    "prediction_date": "2026-03-19T12:36:05.682461",
    "home_win_prob": 0.4685108959674835,
    "away_win_prob": 0.5314890742301941,
    "predicted_winner": "Texas A&M",
    "predicted_home_win": 0,
    "confidence": 0.5314890742301941,
    "model_name": "AdaptivePredictor",
    "model_version": "25c5331",
    "config_version": "7dd58a0bb0e2",
    "commit_hash": "3fcec26",
    "source": "live",
    "created_at": "2026-03-12T12:34:39.915529",
    "explanation": "Texas A&M is narrowly favored: they are significantly stronger overall, they have a vastly superior defense, and they have a major offensive advantage.",
    "game_date": "2026-03-19T00:00:00",
    "home_team": "Saint Mary's",
    "away_team": "Texas A&M",
    "home_moneyline": -162,
    "away_moneyline": 136
  },
  {
    "id": 15361,
    "game_id": "401856518",
    "prediction_date": "2026-03-19T12:36:05.683403",
    "home_win_prob": 0.4685108959674835,
    "away_win_prob": 0.5314890742301941,
    "predicted_winner": "Missouri",
    "predicted_home_win": 0,
    "confidence": 0.5314890742301941,
    "model_name": "AdaptivePredictor",
    "model_version": "25c5331",
    "config_version": "7dd58a0bb0e2",
    "commit_hash": "3fcec26",
    "source": "live",
    "created_at": "2026-03-13T12:34:40.517091",
    "explanation": "Missouri is narrowly favored: they are dominant at their home venue, they are significantly stronger overall, and they have a major offensive advantage.",
    "game_date": "2026-03-20T00:00:00",
    "home_team": "Miami (FL)",
    "away_team": "Missouri",
    "home_moneyline": -130,
    "away_moneyline": 110
  },
  {
    "id": 15352,
    "game_id": "401856527",
    "prediction_date": "2026-03-19T12:36:05.683042",
    "home_win_prob": 0.4685108959674835,
    "away_win_prob": 0.5314890742301941,
    "predicted_winner": "Miami (OH)",
    "predicted_home_win": 0,
    "confidence": 0.5314890742301941,
    "model_name": "AdaptivePredictor",
    "model_version": "25c5331",
    "config_version": "7dd58a0bb0e2",
    "commit_hash": "3fcec26",
    "source": "live",
    "created_at": "2026-03-13T12:34:40.489939",
    "explanation": "Miami (OH) is narrowly favored: they are significantly stronger overall, they have a major offensive advantage, and they have a vastly superior defense.",
    "game_date": "2026-03-20T00:00:00",
    "home_team": "Tennessee",
    "away_team": "Miami (OH)",
    "home_moneyline": -600,
    "away_moneyline": 440
  }
]