[
  {
    "game_id": "401825508",
    "date": "2026-02-11",
    "season": "2025-26",
    "home_team": "Maryland",
    "away_team": "Iowa",
    "home_team_id": "120",
    "away_team_id": "2294",
    "home_score": 0,
    "away_score": 0,
    "game_status": "Scheduled",
    "neutral_site": false,
    "home_moneyline": 470,
    "away_moneyline": -650,
    "venue": null,
    "tournament": null,
    "conference_game": false,
    "created_at": "2026-02-04T12:33:51.007788",
    "updated_at": "2026-02-11T12:18:29.162228",
    "id": 13838,
    "prediction_date": "2026-02-11T12:39:50.538922",
    "home_win_prob": 0.208078533411026,
    "away_win_prob": 0.7919214367866516,
    "predicted_winner": "Iowa",
    "predicted_home_win": 0,
    "confidence": 0.7919214367866516,
    "model_name": "AdaptivePredictor",
    "model_version": "ad6af36",
    "config_version": "7dd58a0bb0e2",
    "commit_hash": "9d65895",
    "source": "live",
    "explanation": "Iowa is confidently favored: they are significantly stronger overall, they have a vastly superior defense, and they have a major offensive advantage."
  },
  {
    "game_id": "401827677",
    "date": "2026-02-11",
    "season": "2025-26",
    "home_team": "Kansas State",
    "away_team": "Cincinnati",
    "home_team_id": "2306",
    "away_team_id": "2132",
    "home_score": 0,
    "away_score": 0,
    "game_status": "Scheduled",
    "neutral_site": false,
    "home_moneyline": 114,
    "away_moneyline": -135,
    "venue": null,
    "tournament": null,
    "conference_game": false,
    "created_at": "2026-02-04T12:33:51.152880",
    "updated_at": "2026-02-11T12:18:29.162228",
    "id": 13880,
    "prediction_date": "2026-02-11T12:39:50.540453",
    "home_win_prob": 0.9900000095367432,
    "away_win_prob": 0.009999999776482582,
    "predicted_winner": "Kansas State",
    "predicted_home_win": 1,
    "confidence": 0.8500000238418579,
    "model_name": "AdaptivePredictor",
    "model_version": "ad6af36",
    "config_version": "7dd58a0bb0e2",
    "commit_hash": "9d65895",
    "source": "live",
    "explanation": "Kansas State is strongly favored: they are significantly stronger overall, they are dominant at their home venue, and they have faced much tougher competition."
  },
  {
    "game_id": "401824372",
    "date": "2026-02-11",
    "season": "2025-26",
    "home_team": "Army Black",
    "away_team": "Boston University",
    "home_team_id": "349",
    "away_team_id": "104",
    "home_score": 0,
    "away_score": 0,
    "game_status": "Scheduled",
    "neutral_site": false,
    "home_moneyline": 136,
    "away_moneyline": -162,
    "venue": null,
    "tournament": null,
    "conference_game": false,
    "created_at": "2026-02-04T12:33:51.015033",
    "updated_at": "2026-02-11T12:18:29.162228",
    "id": 13840,
    "prediction_date": "2026-02-11T12:39:50.539027",
    "home_win_prob": 0.5134929418563843,
    "away_win_prob": 0.4865070581436157,
    "predicted_winner": "Army",
    "predicted_home_win": 1,
    "confidence": 0.5134929418563843,
    "model_name": "AdaptivePredictor",
    "model_version": "ad6af36",
    "config_version": "7dd58a0bb0e2",
    "commit_hash": "9d65895",
    "source": "live",
    "explanation": "Army is narrowly favored: they are significantly stronger overall, they have a vastly superior defense, and they have a major offensive advantage."
  },
  {
    "game_id": "401809367",
    "date": "2026-02-11",
    "season": "2025-26",
    "home_team": "Western Carolina",
    "away_team": "The Citadel",
    "home_team_id": "2717",
    "away_team_id": "2643",
    "home_score": 0,
    "away_score": 0,
    "game_status": "Scheduled",
    "neutral_site": false,
    "home_moneyline": -395,
    "away_moneyline": 310,
    "venue": null,
    "tournament": null,
    "conference_game": false,
    "created_at": "2026-02-04T12:33:51.018588",
    "updated_at": "2026-02-11T12:18:29.162228",
    "id": 13841,
    "prediction_date": "2026-02-11T12:39:50.539067",
    "home_win_prob": 0.6401592493057251,
    "away_win_prob": 0.3598407804965973,
    "predicted_winner": "Western Carolina",
    "predicted_home_win": 1,
    "confidence": 0.6401592493057251,
    "model_name": "AdaptivePredictor",
    "model_version": "ad6af36",
    "config_version": "7dd58a0bb0e2",
    "commit_hash": "9d65895",
    "source": "live",
    "explanation": "Western Carolina is narrowly favored: they are significantly stronger overall, they have a vastly superior defense, and they have a major offensive advantage."
  },
  {
    "game_id": "401828423",
    "date": "2026-02-11",
    "season": "2025-26",
    "home_team": "La Salle",
    "away_team": "VCU",
    "home_team_id": "2325",
    "away_team_id": "2670",
    "home_score": 0,
    "away_score": 0,
    "game_status": "Scheduled",
    "neutral_site": false,
    "home_moneyline": 600,
    "away_moneyline": -900,
    "venue": null,
    "tournament": null,
    "conference_game": false,
    "created_at": "2026-02-04T12:33:51.022017",
    "updated_at": "2026-02-11T12:18:29.162228",
    "id": 13842,
    "prediction_date": "2026-02-11T12:39:50.539105",
    "home_win_prob": 0.009999999776482582,
    "away_win_prob": 0.9900000095367432,
    "predicted_winner": "Virginia Commonwealth",
    "predicted_home_win": 0,
    "confidence": 0.8500000238418579,
    "model_name": "AdaptivePredictor",
    "model_version": "ad6af36",
    "config_version": "7dd58a0bb0e2",
    "commit_hash": "9d65895",
    "source": "live",
    "explanation": "Virginia Commonwealth is strongly favored: they are significantly stronger overall, they have a vastly superior defense, and they have a major offensive advantage."
  },
  {
    "game_id": "401825510",
    "date": "2026-02-11",
    "season": "2025-26",
    "home_team": "Ohio State",
    "away_team": "USC",
    "home_team_id": "194",
    "away_team_id": "30",
    "home_score": 0,
    "away_score": 0,
    "game_status": "Scheduled",
    "neutral_site": false,
    "home_moneyline": -340,
    "away_moneyline": 270,
    "venue": null,
    "tournament": null,
    "conference_game": false,
    "created_at": "2026-02-04T12:33:51.025553",
    "updated_at": "2026-02-11T12:18:29.162228",
    "id": 13843,
    "prediction_date": "2026-02-11T12:39:50.539144",
    "home_win_prob": 0.208078533411026,
    "away_win_prob": 0.7919214367866516,
    "predicted_winner": "USC",
    "predicted_home_win": 0,
    "confidence": 0.7919214367866516,
    "model_name": "AdaptivePredictor",
    "model_version": "ad6af36",
    "config_version": "7dd58a0bb0e2",
    "commit_hash": "9d65895",
    "source": "live",
    "explanation": "USC is confidently favored: they are significantly stronger overall, they have a vastly superior defense, and they have a major offensive advantage."
  },
  {
    "game_id": "401808230",
    "date": "2026-02-11",
    "season": "2025-26",
    "home_team": "Georgia",
    "away_team": "Florida",
    "home_team_id": "61",
    "away_team_id": "57",
    "home_score": 0,
    "away_score": 0,
    "game_status": "Scheduled",
    "neutral_site": false,
    "home_moneyline": 340,
    "away_moneyline": -440,
    "venue": null,
    "tournament": null,
    "conference_game": false,
    "created_at": "2026-02-04T12:33:51.029053",
    "updated_at": "2026-02-11T12:18:29.162228",
    "id": 13844,
    "prediction_date": "2026-02-11T12:39:50.539181",
    "home_win_prob": 0.2620587646961212,
    "away_win_prob": 0.7379412651062012,
    "predicted_winner": "Florida",
    "predicted_home_win": 0,
    "confidence": 0.7379412651062012,
    "model_name": "AdaptivePredictor",
    "model_version": "ad6af36",
    "config_version": "7dd58a0bb0e2",
    "commit_hash": "9d65895",
    "source": "live",
    "explanation": "Florida is favored: they are significantly stronger overall, they have a major offensive advantage, and they have a vastly superior defense."
  },
  {
    "game_id": "401820733",
    "date": "2026-02-11",
    "season": "2025-26",
    "home_team": "Clemson",
    "away_team": "Virginia Tech",
    "home_team_id": "228",
    "away_team_id": "259",
    "home_score": 0,
    "away_score": 0,
    "game_status": "Scheduled",
    "neutral_site": false,
    "home_moneyline": null,
    "away_moneyline": null,
    "venue": null,
    "tournament": null,
    "conference_game": false,
    "created_at": "2026-02-04T12:33:51.032319",
    "updated_at": "2026-02-11T12:18:29.162228",
    "id": 13845,
    "prediction_date": "2026-02-11T12:39:50.539217",
    "home_win_prob": 0.8689194321632385,
    "away_win_prob": 0.13108059763908386,
    "predicted_winner": "Clemson",
    "predicted_home_win": 1,
    "confidence": 0.8500000238418579,
    "model_name": "AdaptivePredictor",
    "model_version": "ad6af36",
    "config_version": "7dd58a0bb0e2",
    "commit_hash": "9d65895",
    "source": "live",
    "explanation": "Clemson is strongly favored: they are significantly stronger overall, they have a vastly superior defense, and they have a major offensive advantage."
  },
  {
    "game_id": "401828677",
    "date": "2026-02-11",
    "season": "2025-26",
    "home_team": "Lehigh Mountain",
    "away_team": "American University",
    "home_team_id": "2329",
    "away_team_id": "44",
    "home_score": 0,
    "away_score": 0,
    "game_status": "Scheduled",
    "neutral_site": false,
    "home_moneyline": 105,
    "away_moneyline": -125,
    "venue": null,
    "tournament": null,
    "conference_game": false,
    "created_at": "2026-02-04T12:33:51.035668",
    "updated_at": "2026-02-11T12:18:29.162228",
    "id": 13846,
    "prediction_date": "2026-02-11T12:39:50.539254",
    "home_win_prob": 0.40433648228645325,
    "away_win_prob": 0.5956635475158691,
    "predicted_winner": "American University",
    "predicted_home_win": 0,
    "confidence": 0.5956635475158691,
    "model_name": "AdaptivePredictor",
    "model_version": "ad6af36",
    "config_version": "7dd58a0bb0e2",
    "commit_hash": "9d65895",
    "source": "live",
    "explanation": "American University is narrowly favored: they are significantly stronger overall, they have a vastly superior defense, and they have a major offensive advantage."
  },
  {
    "game_id": "401828221",
    "date": "2026-02-11",
    "season": "2025-26",
    "home_team": "East Carolina",
    "away_team": "UTSA",
    "home_team_id": "151",
    "away_team_id": "2636",
    "home_score": 0,
    "away_score": 0,
    "game_status": "Scheduled",
    "neutral_site": false,
    "home_moneyline": -625,
    "away_moneyline": 455,
    "venue": null,
    "tournament": null,
    "conference_game": false,
    "created_at": "2026-02-04T12:33:51.039165",
    "updated_at": "2026-02-11T12:18:29.162228",
    "id": 13847,
    "prediction_date": "2026-02-11T12:39:50.539291",
    "home_win_prob": 0.9900000095367432,
    "away_win_prob": 0.009999999776482582,
    "predicted_winner": "East Carolina",
    "predicted_home_win": 1,
    "confidence": 0.8500000238418579,
    "model_name": "AdaptivePredictor",
    "model_version": "ad6af36",
    "config_version": "7dd58a0bb0e2",
    "commit_hash": "9d65895",
    "source": "live",
    "explanation": "East Carolina is strongly favored: they are significantly stronger overall, they have a vastly superior defense, and they have a major offensive advantage."
  },
  {
    "game_id": "401820738",
    "date": "2026-02-11",
    "season": "2025-26",
    "home_team": "Syracuse Orange",
    "away_team": "California",
    "home_team_id": "183",
    "away_team_id": "25",
    "home_score": 0,
    "away_score": 0,
    "game_status": "Scheduled",
    "neutral_site": false,
    "home_moneyline": -230,
    "away_moneyline": 190,
    "venue": null,
    "tournament": null,
    "conference_game": false,
    "created_at": "2026-02-04T12:33:51.042854",
    "updated_at": "2026-02-11T12:18:29.162228",
    "id": 13848,
    "prediction_date": "2026-02-11T12:39:50.539328",
    "home_win_prob": 0.5134929418563843,
    "away_win_prob": 0.4865070581436157,
    "predicted_winner": "Syracuse Orange",
    "predicted_home_win": 1,
    "confidence": 0.5134929418563843,
    "model_name": "AdaptivePredictor",
    "model_version": "ad6af36",
    "config_version": "7dd58a0bb0e2",
    "commit_hash": "9d65895",
    "source": "live",
    "explanation": "Syracuse Orange is narrowly favored: they are significantly stronger overall, they have a vastly superior defense, and they have a major offensive advantage."
  },
  {
    "game_id": "401820204",
    "date": "2026-02-11",
    "season": "2025-26",
    "home_team": "Lafayette",
    "away_team": "Loyola Maryland",
    "home_team_id": "322",
    "away_team_id": "2352",
    "home_score": 0,
    "away_score": 0,
    "game_status": "Scheduled",
    "neutral_site": false,
    "home_moneyline": -155,
    "away_moneyline": 130,
    "venue": null,
    "tournament": null,
    "conference_game": false,
    "created_at": "2026-02-04T12:33:51.046179",
    "updated_at": "2026-02-11T12:18:29.162228",
    "id": 13849,
    "prediction_date": "2026-02-11T12:39:50.539364",
    "home_win_prob": 0.6401592493057251,
    "away_win_prob": 0.3598407804965973,
    "predicted_winner": "Lafayette",
    "predicted_home_win": 1,
    "confidence": 0.6401592493057251,
    "model_name": "AdaptivePredictor",
    "model_version": "ad6af36",
    "config_version": "7dd58a0bb0e2",
    "commit_hash": "9d65895",
    "source": "live",
    "explanation": "Lafayette is narrowly favored: they are significantly stronger overall, they have a vastly superior defense, and they have a major offensive advantage."
  },
  {
    "game_id": "401814561",
    "date": "2026-02-11",
    "season": "2025-26",
    "home_team": "Western Michigan",
    "away_team": "Toledo",
    "home_team_id": "2711",
    "away_team_id": "2649",
    "home_score": 0,
    "away_score": 0,
    "game_status": "Scheduled",
    "neutral_site": false,
    "home_moneyline": 225,
    "away_moneyline": -278,
    "venue": null,
    "tournament": null,
    "conference_game": false,
    "created_at": "2026-02-04T12:33:51.049696",
    "updated_at": "2026-02-11T12:18:29.162228",
    "id": 13850,
    "prediction_date": "2026-02-11T12:39:50.539400",
    "home_win_prob": 0.40433648228645325,
    "away_win_prob": 0.5956635475158691,
    "predicted_winner": "Toledo",
    "predicted_home_win": 0,
    "confidence": 0.5956635475158691,
    "model_name": "AdaptivePredictor",
    "model_version": "ad6af36",
    "config_version": "7dd58a0bb0e2",
    "commit_hash": "9d65895",
    "source": "live",
    "explanation": "Toledo is narrowly favored: they are significantly stronger overall, they have a vastly superior defense, and they have a major offensive advantage."
  },
  {
    "game_id": "401814560",
    "date": "2026-02-11",
    "season": "2025-26",
    "home_team": "Kent State Golden Flashes",
    "away_team": "Eastern Michigan",
    "home_team_id": "2309",
    "away_team_id": "2199",
    "home_score": 0,
    "away_score": 0,
    "game_status": "Scheduled",
    "neutral_site": false,
    "home_moneyline": -625,
    "away_moneyline": 455,
    "venue": null,
    "tournament": null,
    "conference_game": false,
    "created_at": "2026-02-04T12:33:51.052846",
    "updated_at": "2026-02-11T12:18:29.162228",
    "id": 13851,
    "prediction_date": "2026-02-11T12:39:50.539436",
    "home_win_prob": 0.9900000095367432,
    "away_win_prob": 0.009999999776482582,
    "predicted_winner": "Kent State Golden Flashes",
    "predicted_home_win": 1,
    "confidence": 0.8500000238418579,
    "model_name": "AdaptivePredictor",
    "model_version": "ad6af36",
    "config_version": "7dd58a0bb0e2",
    "commit_hash": "9d65895",
    "source": "live",
    "explanation": "Kent State Golden Flashes is strongly favored: they are significantly stronger overall, they have a vastly superior defense, and they have a major offensive advantage."
  },
  {
    "game_id": "401824393",
    "date": "2026-02-11",
    "season": "2025-26",
    "home_team": "Holy Cross",
    "away_team": "Colgate",
    "home_team_id": "107",
    "away_team_id": "2142",
    "home_score": 0,
    "away_score": 0,
    "game_status": "Scheduled",
    "neutral_site": false,
    "home_moneyline": 250,
    "away_moneyline": -310,
    "venue": null,
    "tournament": null,
    "conference_game": false,
    "created_at": "2026-02-04T12:33:51.011568",
    "updated_at": "2026-02-11T12:18:29.162228",
    "id": 13839,
    "prediction_date": "2026-02-11T12:39:50.538983",
    "home_win_prob": 0.208078533411026,
    "away_win_prob": 0.7919214367866516,
    "predicted_winner": "Colgate",
    "predicted_home_win": 0,
    "confidence": 0.7919214367866516,
    "model_name": "AdaptivePredictor",
    "model_version": "ad6af36",
    "config_version": "7dd58a0bb0e2",
    "commit_hash": "9d65895",
    "source": "live",
    "explanation": "Colgate is confidently favored: they are significantly stronger overall, they have a vastly superior defense, and they have a major offensive advantage."
  },
  {
    "game_id": "401809366",
    "date": "2026-02-11",
    "season": "2025-26",
    "home_team": "UNC Greensboro",
    "away_team": "VMI",
    "home_team_id": "2430",
    "away_team_id": "2678",
    "home_score": 0,
    "away_score": 0,
    "game_status": "Scheduled",
    "neutral_site": false,
    "home_moneyline": -410,
    "away_moneyline": 320,
    "venue": null,
    "tournament": null,
    "conference_game": false,
    "created_at": "2026-02-04T12:33:51.060226",
    "updated_at": "2026-02-11T12:18:29.162228",
    "id": 13853,
    "prediction_date": "2026-02-11T12:39:50.539508",
    "home_win_prob": 0.9900000095367432,
    "away_win_prob": 0.009999999776482582,
    "predicted_winner": "UNC Greensboro",
    "predicted_home_win": 1,
    "confidence": 0.8500000238418579,
    "model_name": "AdaptivePredictor",
    "model_version": "ad6af36",
    "config_version": "7dd58a0bb0e2",
    "commit_hash": "9d65895",
    "source": "live",
    "explanation": "UNC Greensboro is strongly favored: they are significantly stronger overall, they have a vastly superior defense, and they have a major offensive advantage."
  },
  {
    "game_id": "401809365",
    "date": "2026-02-11",
    "season": "2025-26",
    "home_team": "Samford",
    "away_team": "Wofford",
    "home_team_id": "2535",
    "away_team_id": "2747",
    "home_score": 0,
    "away_score": 0,
    "game_status": "Scheduled",
    "neutral_site": false,
    "home_moneyline": -198,
    "away_moneyline": 164,
    "venue": null,
    "tournament": null,
    "conference_game": false,
    "created_at": "2026-02-04T12:33:51.063840",
    "updated_at": "2026-02-11T12:18:29.162228",
    "id": 13854,
    "prediction_date": "2026-02-11T12:39:50.539544",
    "home_win_prob": 0.2620587646961212,
    "away_win_prob": 0.7379412651062012,
    "predicted_winner": "Wofford",
    "predicted_home_win": 0,
    "confidence": 0.7379412651062012,
    "model_name": "AdaptivePredictor",
    "model_version": "ad6af36",
    "config_version": "7dd58a0bb0e2",
    "commit_hash": "9d65895",
    "source": "live",
    "explanation": "Wofford is favored: they are significantly stronger overall, they have a vastly superior defense, and they have a major offensive advantage."
  },
  {
    "game_id": "401809364",
    "date": "2026-02-11",
    "season": "2025-26",
    "home_team": "Mercer",
    "away_team": "Furman",
    "home_team_id": "2382",
    "away_team_id": "231",
    "home_score": 0,
    "away_score": 0,
    "game_status": "Scheduled",
    "neutral_site": false,
    "home_moneyline": -155,
    "away_moneyline": 130,
    "venue": null,
    "tournament": null,
    "conference_game": false,
    "created_at": "2026-02-04T12:33:51.067730",
    "updated_at": "2026-02-11T12:18:29.162228",
    "id": 13855,
    "prediction_date": "2026-02-11T12:39:50.539581",
    "home_win_prob": 0.9900000095367432,
    "away_win_prob": 0.009999999776482582,
    "predicted_winner": "Mercer",
    "predicted_home_win": 1,
    "confidence": 0.8500000238418579,
    "model_name": "AdaptivePredictor",
    "model_version": "ad6af36",
    "config_version": "7dd58a0bb0e2",
    "commit_hash": "9d65895",
    "source": "live",
    "explanation": "Mercer is strongly favored: they are significantly stronger overall, they have a vastly superior defense, and they have a major offensive advantage."
  },
  {
    "game_id": "401809363",
    "date": "2026-02-11",
    "season": "2025-26",
    "home_team": "East Tennessee State",
    "away_team": "Chattanooga Mocs",
    "home_team_id": "2193",
    "away_team_id": "236",
    "home_score": 0,
    "away_score": 0,
    "game_status": "Scheduled",
    "neutral_site": false,
    "home_moneyline": -700,
    "away_moneyline": 500,
    "venue": null,
    "tournament": null,
    "conference_game": false,
    "created_at": "2026-02-04T12:33:51.071197",
    "updated_at": "2026-02-11T12:18:29.162228",
    "id": 13856,
    "prediction_date": "2026-02-11T12:39:50.539617",
    "home_win_prob": 0.865406334400177,
    "away_win_prob": 0.1345936805009842,
    "predicted_winner": "East Tennessee State",
    "predicted_home_win": 1,
    "confidence": 0.8500000238418579,
    "model_name": "AdaptivePredictor",
    "model_version": "ad6af36",
    "config_version": "7dd58a0bb0e2",
    "commit_hash": "9d65895",
    "source": "live",
    "explanation": "East Tennessee State is strongly favored: they are significantly stronger overall, they have a vastly superior defense, and they have a major offensive advantage."
  },
  {
    "game_id": "401808227",
    "date": "2026-02-11",
    "season": "2025-26",
    "home_team": "Ole Miss",
    "away_team": "Alabama Crimson Tide",
    "home_team_id": "145",
    "away_team_id": "333",
    "home_score": 0,
    "away_score": 0,
    "game_status": "Scheduled",
    "neutral_site": false,
    "home_moneyline": 260,
    "away_moneyline": -325,
    "venue": null,
    "tournament": null,
    "conference_game": false,
    "created_at": "2026-02-04T12:33:51.077804",
    "updated_at": "2026-02-11T12:18:29.162228",
    "id": 13858,
    "prediction_date": "2026-02-11T12:39:50.539653",
    "home_win_prob": 0.11472060531377792,
    "away_win_prob": 0.8852794170379639,
    "predicted_winner": "Alabama Crimson Tide",
    "predicted_home_win": 0,
    "confidence": 0.8500000238418579,
    "model_name": "AdaptivePredictor",
    "model_version": "ad6af36",
    "config_version": "7dd58a0bb0e2",
    "commit_hash": "9d65895",
    "source": "live",
    "explanation": "Alabama Crimson Tide is strongly favored: they are significantly stronger overall, they have a vastly superior defense, and they have a major offensive advantage."
  },
  {
    "game_id": "401807738",
    "date": "2026-02-11",
    "season": "2025-26",
    "home_team": "North Alabama",
    "away_team": "West Georgia",
    "home_team_id": "2453",
    "away_team_id": "2698",
    "home_score": 0,
    "away_score": 0,
    "game_status": "Scheduled",
    "neutral_site": false,
    "home_moneyline": -118,
    "away_moneyline": -102,
    "venue": null,
    "tournament": null,
    "conference_game": false,
    "created_at": "2026-02-04T12:33:51.081181",
    "updated_at": "2026-02-11T12:18:29.162228",
    "id": 13859,
    "prediction_date": "2026-02-11T12:39:50.539688",
    "home_win_prob": 0.014810717664659023,
    "away_win_prob": 0.9851892590522766,
    "predicted_winner": "West Georgia",
    "predicted_home_win": 0,
    "confidence": 0.8500000238418579,
    "model_name": "AdaptivePredictor",
    "model_version": "ad6af36",
    "config_version": "7dd58a0bb0e2",
    "commit_hash": "9d65895",
    "source": "live",
    "explanation": "West Georgia is strongly favored: they are significantly stronger overall, they have a vastly superior defense, and they have a major offensive advantage."
  },
  {
    "game_id": "401807737",
    "date": "2026-02-11",
    "season": "2025-26",
    "home_team": "Florida Gulf Coast",
    "away_team": "North Florida Ospreys",
    "home_team_id": "526",
    "away_team_id": "2454",
    "home_score": 0,
    "away_score": 0,
    "game_status": "Scheduled",
    "neutral_site": false,
    "home_moneyline": -900,
    "away_moneyline": 600,
    "venue": null,
    "tournament": null,
    "conference_game": false,
    "created_at": "2026-02-04T12:33:51.084407",
    "updated_at": "2026-02-11T12:18:29.162228",
    "id": 13860,
    "prediction_date": "2026-02-11T12:39:50.539725",
    "home_win_prob": 0.6401592493057251,
    "away_win_prob": 0.3598407804965973,
    "predicted_winner": "Florida Gulf Coast",
    "predicted_home_win": 1,
    "confidence": 0.6401592493057251,
    "model_name": "AdaptivePredictor",
    "model_version": "ad6af36",
    "config_version": "7dd58a0bb0e2",
    "commit_hash": "9d65895",
    "source": "live",
    "explanation": "Florida Gulf Coast is narrowly favored: they are significantly stronger overall, they have a vastly superior defense, and they have a major offensive advantage."
  },
  {
    "game_id": "401807736",
    "date": "2026-02-11",
    "season": "2025-26",
    "home_team": "Stetson",
    "away_team": "Jacksonville",
    "home_team_id": "56",
    "away_team_id": "294",
    "home_score": 0,
    "away_score": 0,
    "game_status": "Scheduled",
    "neutral_site": false,
    "home_moneyline": 110,
    "away_moneyline": -130,
    "venue": null,
    "tournament": null,
    "conference_game": false,
    "created_at": "2026-02-04T12:33:51.087854",
    "updated_at": "2026-02-11T12:18:29.162228",
    "id": 13861,
    "prediction_date": "2026-02-11T12:39:50.539760",
    "home_win_prob": 0.6401592493057251,
    "away_win_prob": 0.3598407804965973,
    "predicted_winner": "Stetson",
    "predicted_home_win": 1,
    "confidence": 0.6401592493057251,
    "model_name": "AdaptivePredictor",
    "model_version": "ad6af36",
    "config_version": "7dd58a0bb0e2",
    "commit_hash": "9d65895",
    "source": "live",
    "explanation": "Stetson is narrowly favored: they are significantly stronger overall, they have a vastly superior defense, and they have a major offensive advantage."
  },
  {
    "game_id": "401807733",
    "date": "2026-02-11",
    "season": "2025-26",
    "home_team": "Queens University",
    "away_team": "Austin Peay Governors",
    "home_team_id": "2511",
    "away_team_id": "2046",
    "home_score": 0,
    "away_score": 0,
    "game_status": "Scheduled",
    "neutral_site": false,
    "home_moneyline": -135,
    "away_moneyline": 114,
    "venue": null,
    "tournament": null,
    "conference_game": false,
    "created_at": "2026-02-04T12:33:51.091489",
    "updated_at": "2026-02-11T12:18:29.162228",
    "id": 13862,
    "prediction_date": "2026-02-11T12:39:50.539796",
    "home_win_prob": 0.5488553047180176,
    "away_win_prob": 0.45114466547966003,
    "predicted_winner": "Queens University",
    "predicted_home_win": 1,
    "confidence": 0.5488553047180176,
    "model_name": "AdaptivePredictor",
    "model_version": "ad6af36",
    "config_version": "7dd58a0bb0e2",
    "commit_hash": "9d65895",
    "source": "live",
    "explanation": "Queens University is narrowly favored: they are significantly stronger overall, they have a vastly superior defense, and they have a major offensive advantage."
  },
  {
    "game_id": "401804923",
    "date": "2026-02-11",
    "season": "2025-26",
    "home_team": "Jacksonville State",
    "away_team": "UTEP",
    "home_team_id": "55",
    "away_team_id": "2638",
    "home_score": 0,
    "away_score": 0,
    "game_status": "Scheduled",
    "neutral_site": false,
    "home_moneyline": -340,
    "away_moneyline": 270,
    "venue": null,
    "tournament": null,
    "conference_game": false,
    "created_at": "2026-02-04T12:33:51.094762",
    "updated_at": "2026-02-11T12:18:29.162228",
    "id": 13863,
    "prediction_date": "2026-02-11T12:39:50.539831",
    "home_win_prob": 0.8689194321632385,
    "away_win_prob": 0.13108059763908386,
    "predicted_winner": "Jacksonville State",
    "predicted_home_win": 1,
    "confidence": 0.8500000238418579,
    "model_name": "AdaptivePredictor",
    "model_version": "ad6af36",
    "config_version": "7dd58a0bb0e2",
    "commit_hash": "9d65895",
    "source": "live",
    "explanation": "Jacksonville State is strongly favored: they are dominant at their home venue, they are significantly stronger overall, and they have faced much tougher competition."
  },
  {
    "game_id": "401822940",
    "date": "2026-02-11",
    "season": "2025-26",
    "home_team": "Butler",
    "away_team": "UConn",
    "home_team_id": "2086",
    "away_team_id": "41",
    "home_score": 0,
    "away_score": 0,
    "game_status": "Scheduled",
    "neutral_site": false,
    "home_moneyline": null,
    "away_moneyline": null,
    "venue": null,
    "tournament": null,
    "conference_game": false,
    "created_at": "2026-02-04T12:33:51.098243",
    "updated_at": "2026-02-11T12:18:29.162228",
    "id": 13864,
    "prediction_date": "2026-02-11T12:39:50.539878",
    "home_win_prob": 0.009999999776482582,
    "away_win_prob": 0.9900000095367432,
    "predicted_winner": "UConn",
    "predicted_home_win": 0,
    "confidence": 0.8500000238418579,
    "model_name": "AdaptivePredictor",
    "model_version": "ad6af36",
    "config_version": "7dd58a0bb0e2",
    "commit_hash": "9d65895",
    "source": "live",
    "explanation": "UConn is strongly favored: they are significantly stronger overall, they have a vastly superior defense, and they have a major offensive advantage."
  },
  {
    "game_id": "401828224",
    "date": "2026-02-11",
    "season": "2025-26",
    "home_team": "Tulane Green Wave",
    "away_team": "Temple",
    "home_team_id": "2655",
    "away_team_id": "218",
    "home_score": 0,
    "away_score": 0,
    "game_status": "Scheduled",
    "neutral_site": false,
    "home_moneyline": -110,
    "away_moneyline": -110,
    "venue": null,
    "tournament": null,
    "conference_game": false,
    "created_at": "2026-02-04T12:33:51.101797",
    "updated_at": "2026-02-11T12:18:29.162228",
    "id": 13865,
    "prediction_date": "2026-02-11T12:39:50.539914",
    "home_win_prob": 0.014810717664659023,
    "away_win_prob": 0.9851892590522766,
    "predicted_winner": "Temple",
    "predicted_home_win": 0,
    "confidence": 0.8500000238418579,
    "model_name": "AdaptivePredictor",
    "model_version": "ad6af36",
    "config_version": "7dd58a0bb0e2",
    "commit_hash": "9d65895",
    "source": "live",
    "explanation": "Temple is strongly favored: they are significantly stronger overall, they have a vastly superior defense, and they have a major offensive advantage."
  },
  {
    "game_id": "401828223",
    "date": "2026-02-11",
    "season": "2025-26",
    "home_team": "Wichita State",
    "away_team": "South Florida",
    "home_team_id": "2724",
    "away_team_id": "58",
    "home_score": 0,
    "away_score": 0,
    "game_status": "Scheduled",
    "neutral_site": false,
    "home_moneyline": -108,
    "away_moneyline": -112,
    "venue": null,
    "tournament": null,
    "conference_game": false,
    "created_at": "2026-02-04T12:33:51.104976",
    "updated_at": "2026-02-11T12:18:29.162228",
    "id": 13866,
    "prediction_date": "2026-02-11T12:39:50.539951",
    "home_win_prob": 0.5134929418563843,
    "away_win_prob": 0.4865070581436157,
    "predicted_winner": "Wichita State",
    "predicted_home_win": 1,
    "confidence": 0.5134929418563843,
    "model_name": "AdaptivePredictor",
    "model_version": "ad6af36",
    "config_version": "7dd58a0bb0e2",
    "commit_hash": "9d65895",
    "source": "live",
    "explanation": "Wichita State is narrowly favored: they are significantly stronger overall, they have a vastly superior defense, and they have a major offensive advantage."
  },
  {
    "game_id": "401822941",
    "date": "2026-02-11",
    "season": "2025-26",
    "home_team": "Seton Hall",
    "away_team": "Providence",
    "home_team_id": "2550",
    "away_team_id": "2507",
    "home_score": 0,
    "away_score": 0,
    "game_status": "Scheduled",
    "neutral_site": false,
    "home_moneyline": null,
    "away_moneyline": null,
    "venue": null,
    "tournament": null,
    "conference_game": false,
    "created_at": "2026-02-04T12:33:51.108318",
    "updated_at": "2026-02-11T12:18:29.162228",
    "id": 13867,
    "prediction_date": "2026-02-11T12:39:50.539986",
    "home_win_prob": 0.865406334400177,
    "away_win_prob": 0.1345936805009842,
    "predicted_winner": "Seton Hall",
    "predicted_home_win": 1,
    "confidence": 0.8500000238418579,
    "model_name": "AdaptivePredictor",
    "model_version": "ad6af36",
    "config_version": "7dd58a0bb0e2",
    "commit_hash": "9d65895",
    "source": "live",
    "explanation": "Seton Hall is strongly favored: they are dominant at their home venue, they are significantly stronger overall, and they have a vastly superior defense."
  },
  {
    "game_id": "401808663",
    "date": "2026-02-11",
    "season": "2025-26",
    "home_team": "Old Dominion",
    "away_team": "Marshall",
    "home_team_id": "295",
    "away_team_id": "276",
    "home_score": 0,
    "away_score": 0,
    "game_status": "Scheduled",
    "neutral_site": false,
    "home_moneyline": 130,
    "away_moneyline": -155,
    "venue": null,
    "tournament": null,
    "conference_game": false,
    "created_at": "2026-02-04T12:33:51.111573",
    "updated_at": "2026-02-11T12:18:29.162228",
    "id": 13868,
    "prediction_date": "2026-02-11T12:39:50.540022",
    "home_win_prob": 0.208078533411026,
    "away_win_prob": 0.7919214367866516,
    "predicted_winner": "Marshall",
    "predicted_home_win": 0,
    "confidence": 0.7919214367866516,
    "model_name": "AdaptivePredictor",
    "model_version": "ad6af36",
    "config_version": "7dd58a0bb0e2",
    "commit_hash": "9d65895",
    "source": "live",
    "explanation": "Marshall is confidently favored: they are significantly stronger overall, they have a vastly superior defense, and they have a major offensive advantage."
  },
  {
    "game_id": "401807735",
    "date": "2026-02-11",
    "season": "2025-26",
    "home_team": "Central Arkansas",
    "away_team": "Bellarmine",
    "home_team_id": "2110",
    "away_team_id": "91",
    "home_score": 0,
    "away_score": 0,
    "game_status": "Scheduled",
    "neutral_site": false,
    "home_moneyline": -355,
    "away_moneyline": 280,
    "venue": null,
    "tournament": null,
    "conference_game": false,
    "created_at": "2026-02-04T12:33:51.115445",
    "updated_at": "2026-02-11T12:18:29.162228",
    "id": 13869,
    "prediction_date": "2026-02-11T12:39:50.540058",
    "home_win_prob": 0.9900000095367432,
    "away_win_prob": 0.009999999776482582,
    "predicted_winner": "Central Arkansas",
    "predicted_home_win": 1,
    "confidence": 0.8500000238418579,
    "model_name": "AdaptivePredictor",
    "model_version": "ad6af36",
    "config_version": "7dd58a0bb0e2",
    "commit_hash": "9d65895",
    "source": "live",
    "explanation": "Central Arkansas is strongly favored: they are significantly stronger overall, they are dominant at their home venue, and they have a vastly superior defense."
  },
  {
    "game_id": "401827678",
    "date": "2026-02-11",
    "season": "2025-26",
    "home_team": "Texas Tech",
    "away_team": "Colorado",
    "home_team_id": "2641",
    "away_team_id": "38",
    "home_score": 0,
    "away_score": 0,
    "game_status": "Scheduled",
    "neutral_site": false,
    "home_moneyline": -1450,
    "away_moneyline": 850,
    "venue": null,
    "tournament": null,
    "conference_game": false,
    "created_at": "2026-02-04T12:33:51.119693",
    "updated_at": "2026-02-11T12:18:29.162228",
    "id": 13870,
    "prediction_date": "2026-02-11T12:39:50.540094",
    "home_win_prob": 0.9900000095367432,
    "away_win_prob": 0.009999999776482582,
    "predicted_winner": "Texas Tech",
    "predicted_home_win": 1,
    "confidence": 0.8500000238418579,
    "model_name": "AdaptivePredictor",
    "model_version": "ad6af36",
    "config_version": "7dd58a0bb0e2",
    "commit_hash": "9d65895",
    "source": "live",
    "explanation": "Texas Tech is strongly favored: they are significantly stronger overall, they have a vastly superior defense, and they have a major offensive advantage."
  },
  {
    "game_id": "401828222",
    "date": "2026-02-11",
    "season": "2025-26",
    "home_team": "Rice",
    "away_team": "Florida Atlantic",
    "home_team_id": "242",
    "away_team_id": "2226",
    "home_score": 0,
    "away_score": 0,
    "game_status": "Scheduled",
    "neutral_site": false,
    "home_moneyline": 136,
    "away_moneyline": -162,
    "venue": null,
    "tournament": null,
    "conference_game": false,
    "created_at": "2026-02-04T12:33:51.122995",
    "updated_at": "2026-02-11T12:18:29.162228",
    "id": 13871,
    "prediction_date": "2026-02-11T12:39:50.540130",
    "home_win_prob": 0.208078533411026,
    "away_win_prob": 0.7919214367866516,
    "predicted_winner": "Florida Atlantic",
    "predicted_home_win": 0,
    "confidence": 0.7919214367866516,
    "model_name": "AdaptivePredictor",
    "model_version": "ad6af36",
    "config_version": "7dd58a0bb0e2",
    "commit_hash": "9d65895",
    "source": "live",
    "explanation": "Florida Atlantic is confidently favored: they are significantly stronger overall, they have a vastly superior defense, and they have a major offensive advantage."
  },
  {
    "game_id": "401828220",
    "date": "2026-02-11",
    "season": "2025-26",
    "home_team": "Tulsa Golden Hurricane",
    "away_team": "UAB",
    "home_team_id": "202",
    "away_team_id": "5",
    "home_score": 0,
    "away_score": 0,
    "game_status": "Scheduled",
    "neutral_site": false,
    "home_moneyline": -600,
    "away_moneyline": 440,
    "venue": null,
    "tournament": null,
    "conference_game": false,
    "created_at": "2026-02-04T12:33:51.126229",
    "updated_at": "2026-02-11T12:18:29.162228",
    "id": 13872,
    "prediction_date": "2026-02-11T12:39:50.540166",
    "home_win_prob": 0.2620587646961212,
    "away_win_prob": 0.7379412651062012,
    "predicted_winner": "UAB",
    "predicted_home_win": 0,
    "confidence": 0.7379412651062012,
    "model_name": "AdaptivePredictor",
    "model_version": "ad6af36",
    "config_version": "7dd58a0bb0e2",
    "commit_hash": "9d65895",
    "source": "live",
    "explanation": "UAB is favored: they are significantly stronger overall, they have a vastly superior defense, and they have a major offensive advantage."
  },
  {
    "game_id": "401818416",
    "date": "2026-02-11",
    "season": "2025-26",
    "home_team": "South Dakota",
    "away_team": "North Dakota Fighting",
    "home_team_id": "233",
    "away_team_id": "155",
    "home_score": 0,
    "away_score": 0,
    "game_status": "Scheduled",
    "neutral_site": false,
    "home_moneyline": -122,
    "away_moneyline": 102,
    "venue": null,
    "tournament": null,
    "conference_game": false,
    "created_at": "2026-02-04T12:33:51.129582",
    "updated_at": "2026-02-11T12:18:29.162228",
    "id": 13873,
    "prediction_date": "2026-02-11T12:39:50.540201",
    "home_win_prob": 0.40433648228645325,
    "away_win_prob": 0.5956635475158691,
    "predicted_winner": "North Dakota",
    "predicted_home_win": 0,
    "confidence": 0.5956635475158691,
    "model_name": "AdaptivePredictor",
    "model_version": "ad6af36",
    "config_version": "7dd58a0bb0e2",
    "commit_hash": "9d65895",
    "source": "live",
    "explanation": "North Dakota is narrowly favored: they are significantly stronger overall, they have a vastly superior defense, and they have a major offensive advantage."
  },
  {
    "game_id": "401814558",
    "date": "2026-02-11",
    "season": "2025-26",
    "home_team": "Northern Illinois",
    "away_team": "Bowling Green",
    "home_team_id": "2459",
    "away_team_id": "189",
    "home_score": 0,
    "away_score": 0,
    "game_status": "Scheduled",
    "neutral_site": false,
    "home_moneyline": 225,
    "away_moneyline": -278,
    "venue": null,
    "tournament": null,
    "conference_game": false,
    "created_at": "2026-02-04T12:33:51.132838",
    "updated_at": "2026-02-11T12:18:29.162228",
    "id": 13874,
    "prediction_date": "2026-02-11T12:39:50.540237",
    "home_win_prob": 0.208078533411026,
    "away_win_prob": 0.7919214367866516,
    "predicted_winner": "Bowling Green",
    "predicted_home_win": 0,
    "confidence": 0.7919214367866516,
    "model_name": "AdaptivePredictor",
    "model_version": "ad6af36",
    "config_version": "7dd58a0bb0e2",
    "commit_hash": "9d65895",
    "source": "live",
    "explanation": "Bowling Green is confidently favored: they are significantly stronger overall, they have a vastly superior defense, and they have a major offensive advantage."
  },
  {
    "game_id": "401808665",
    "date": "2026-02-11",
    "season": "2025-26",
    "home_team": "Texas State",
    "away_team": "Troy",
    "home_team_id": "326",
    "away_team_id": "2653",
    "home_score": 0,
    "away_score": 0,
    "game_status": "Scheduled",
    "neutral_site": false,
    "home_moneyline": 185,
    "away_moneyline": -225,
    "venue": null,
    "tournament": null,
    "conference_game": false,
    "created_at": "2026-02-04T12:33:51.136335",
    "updated_at": "2026-02-11T12:18:29.162228",
    "id": 13875,
    "prediction_date": "2026-02-11T12:39:50.540273",
    "home_win_prob": 0.2620587646961212,
    "away_win_prob": 0.7379412651062012,
    "predicted_winner": "Troy",
    "predicted_home_win": 0,
    "confidence": 0.7379412651062012,
    "model_name": "AdaptivePredictor",
    "model_version": "ad6af36",
    "config_version": "7dd58a0bb0e2",
    "commit_hash": "9d65895",
    "source": "live",
    "explanation": "Troy is favored: they are significantly stronger overall, they have a vastly superior defense, and they have a major offensive advantage."
  },
  {
    "game_id": "401808664",
    "date": "2026-02-11",
    "season": "2025-26",
    "home_team": "Arkansas State",
    "away_team": "UL Monroe Warhawks",
    "home_team_id": "2032",
    "away_team_id": "2433",
    "home_score": 0,
    "away_score": 0,
    "game_status": "Scheduled",
    "neutral_site": false,
    "home_moneyline": -3200,
    "away_moneyline": 1400,
    "venue": null,
    "tournament": null,
    "conference_game": false,
    "created_at": "2026-02-04T12:33:51.139495",
    "updated_at": "2026-02-11T12:18:29.162228",
    "id": 13876,
    "prediction_date": "2026-02-11T12:39:50.540310",
    "home_win_prob": 0.8689194321632385,
    "away_win_prob": 0.13108059763908386,
    "predicted_winner": "Arkansas State",
    "predicted_home_win": 1,
    "confidence": 0.8500000238418579,
    "model_name": "AdaptivePredictor",
    "model_version": "ad6af36",
    "config_version": "7dd58a0bb0e2",
    "commit_hash": "9d65895",
    "source": "live",
    "explanation": "Arkansas State is strongly favored: they are significantly stronger overall, they have a vastly superior defense, and they have a major offensive advantage."
  },
  {
    "game_id": "401808662",
    "date": "2026-02-11",
    "season": "2025-26",
    "home_team": "Georgia Southern",
    "away_team": "Appalachian St",
    "home_team_id": "290",
    "away_team_id": "2026",
    "home_score": 0,
    "away_score": 0,
    "game_status": "Scheduled",
    "neutral_site": false,
    "home_moneyline": 120,
    "away_moneyline": -142,
    "venue": null,
    "tournament": null,
    "conference_game": false,
    "created_at": "2026-02-04T12:33:51.074631",
    "updated_at": "2026-02-11T12:18:29.162228",
    "id": 13857,
    "prediction_date": "2026-02-11T12:39:50.540345",
    "home_win_prob": 0.11472060531377792,
    "away_win_prob": 0.8852794170379639,
    "predicted_winner": "Appalachian St",
    "predicted_home_win": 0,
    "confidence": 0.8500000238418579,
    "model_name": "AdaptivePredictor",
    "model_version": "ad6af36",
    "config_version": "7dd58a0bb0e2",
    "commit_hash": "9d65895",
    "source": "live",
    "explanation": "Appalachian St is strongly favored: they are significantly stronger overall, they have a vastly superior defense, and they have a major offensive advantage."
  },
  {
    "game_id": "401807734",
    "date": "2026-02-11",
    "season": "2025-26",
    "home_team": "Lipscomb",
    "away_team": "Eastern Kentucky Colonels",
    "home_team_id": "288",
    "away_team_id": "2198",
    "home_score": 0,
    "away_score": 0,
    "game_status": "Scheduled",
    "neutral_site": false,
    "home_moneyline": -250,
    "away_moneyline": 205,
    "venue": null,
    "tournament": null,
    "conference_game": false,
    "created_at": "2026-02-04T12:33:51.142798",
    "updated_at": "2026-02-11T12:18:29.162228",
    "id": 13877,
    "prediction_date": "2026-02-11T12:39:50.540381",
    "home_win_prob": 0.9900000095367432,
    "away_win_prob": 0.009999999776482582,
    "predicted_winner": "Lipscomb",
    "predicted_home_win": 1,
    "confidence": 0.8500000238418579,
    "model_name": "AdaptivePredictor",
    "model_version": "ad6af36",
    "config_version": "7dd58a0bb0e2",
    "commit_hash": "9d65895",
    "source": "live",
    "explanation": "Lipscomb is strongly favored: they are significantly stronger overall, they have a vastly superior defense, and they have a major offensive advantage."
  },
  {
    "game_id": "401825509",
    "date": "2026-02-11",
    "season": "2025-26",
    "home_team": "Northwestern",
    "away_team": "Michigan",
    "home_team_id": "77",
    "away_team_id": "130",
    "home_score": 0,
    "away_score": 0,
    "game_status": "Scheduled",
    "neutral_site": false,
    "home_moneyline": 950,
    "away_moneyline": -1650,
    "venue": null,
    "tournament": null,
    "conference_game": false,
    "created_at": "2026-02-04T12:33:51.146099",
    "updated_at": "2026-02-11T12:18:29.162228",
    "id": 13878,
    "prediction_date": "2026-02-11T12:39:50.540417",
    "home_win_prob": 0.009999999776482582,
    "away_win_prob": 0.9900000095367432,
    "predicted_winner": "Michigan",
    "predicted_home_win": 0,
    "confidence": 0.8500000238418579,
    "model_name": "AdaptivePredictor",
    "model_version": "ad6af36",
    "config_version": "7dd58a0bb0e2",
    "commit_hash": "9d65895",
    "source": "live",
    "explanation": "Michigan is strongly favored: they are significantly stronger overall, they have a major offensive advantage, and they have a vastly superior defense."
  },
  {
    "game_id": "401825511",
    "date": "2026-02-11",
    "season": "2025-26",
    "home_team": "Washington",
    "away_team": "Penn State",
    "home_team_id": "264",
    "away_team_id": "213",
    "home_score": 0,
    "away_score": 0,
    "game_status": "Scheduled",
    "neutral_site": false,
    "home_moneyline": -1050,
    "away_moneyline": 675,
    "venue": null,
    "tournament": null,
    "conference_game": false,
    "created_at": "2026-02-04T12:33:51.190480",
    "updated_at": "2026-02-11T12:18:29.162228",
    "id": 13891,
    "prediction_date": "2026-02-11T12:39:50.540886",
    "home_win_prob": 0.9900000095367432,
    "away_win_prob": 0.009999999776482582,
    "predicted_winner": "Washington",
    "predicted_home_win": 1,
    "confidence": 0.8500000238418579,
    "model_name": "AdaptivePredictor",
    "model_version": "ad6af36",
    "config_version": "7dd58a0bb0e2",
    "commit_hash": "9d65895",
    "source": "live",
    "explanation": "Washington is strongly favored: they are significantly stronger overall, they have a vastly superior defense, and they are dominant at their home venue."
  },
  {
    "game_id": "401822939",
    "date": "2026-02-11",
    "season": "2025-26",
    "home_team": "DePaul Blue",
    "away_team": "Creighton",
    "home_team_id": "305",
    "away_team_id": "156",
    "home_score": 0,
    "away_score": 0,
    "game_status": "Scheduled",
    "neutral_site": false,
    "home_moneyline": -118,
    "away_moneyline": -102,
    "venue": null,
    "tournament": null,
    "conference_game": false,
    "created_at": "2026-02-04T12:33:51.156269",
    "updated_at": "2026-02-11T12:18:29.162228",
    "id": 13881,
    "prediction_date": "2026-02-11T12:39:50.540489",
    "home_win_prob": 0.5829185843467712,
    "away_win_prob": 0.41708138585090637,
    "predicted_winner": "DePaul Blue",
    "predicted_home_win": 1,
    "confidence": 0.5829185843467712,
    "model_name": "AdaptivePredictor",
    "model_version": "ad6af36",
    "config_version": "7dd58a0bb0e2",
    "commit_hash": "9d65895",
    "source": "live",
    "explanation": "DePaul Blue is narrowly favored: they are significantly stronger overall, they have a vastly superior defense, and they have a major offensive advantage."
  },
  {
    "game_id": "401820735",
    "date": "2026-02-11",
    "season": "2025-26",
    "home_team": "Georgia Tech",
    "away_team": "Wake Forest",
    "home_team_id": "59",
    "away_team_id": "154",
    "home_score": 0,
    "away_score": 0,
    "game_status": "Scheduled",
    "neutral_site": false,
    "home_moneyline": 124,
    "away_moneyline": -148,
    "venue": null,
    "tournament": null,
    "conference_game": false,
    "created_at": "2026-02-04T12:33:51.159646",
    "updated_at": "2026-02-11T12:18:29.162228",
    "id": 13882,
    "prediction_date": "2026-02-11T12:39:50.540525",
    "home_win_prob": 0.40433648228645325,
    "away_win_prob": 0.5956635475158691,
    "predicted_winner": "Wake Forest",
    "predicted_home_win": 0,
    "confidence": 0.5956635475158691,
    "model_name": "AdaptivePredictor",
    "model_version": "ad6af36",
    "config_version": "7dd58a0bb0e2",
    "commit_hash": "9d65895",
    "source": "live",
    "explanation": "Wake Forest is narrowly favored: they are significantly stronger overall, they have a vastly superior defense, and they have a major offensive advantage."
  },
  {
    "game_id": "401820732",
    "date": "2026-02-11",
    "season": "2025-26",
    "home_team": "Boston College",
    "away_team": "Stanford Cardinal",
    "home_team_id": "103",
    "away_team_id": "24",
    "home_score": 0,
    "away_score": 0,
    "game_status": "Scheduled",
    "neutral_site": false,
    "home_moneyline": 110,
    "away_moneyline": -130,
    "venue": null,
    "tournament": null,
    "conference_game": false,
    "created_at": "2026-02-04T12:33:51.163461",
    "updated_at": "2026-02-11T12:18:29.162228",
    "id": 13883,
    "prediction_date": "2026-02-11T12:39:50.540560",
    "home_win_prob": 0.208078533411026,
    "away_win_prob": 0.7919214367866516,
    "predicted_winner": "Stanford Cardinal",
    "predicted_home_win": 0,
    "confidence": 0.7919214367866516,
    "model_name": "AdaptivePredictor",
    "model_version": "ad6af36",
    "config_version": "7dd58a0bb0e2",
    "commit_hash": "9d65895",
    "source": "live",
    "explanation": "Stanford Cardinal is confidently favored: they are significantly stronger overall, they have a vastly superior defense, and they have a major offensive advantage."
  },
  {
    "game_id": "401808232",
    "date": "2026-02-11",
    "season": "2025-26",
    "home_team": "Mississippi State",
    "away_team": "Tennessee",
    "home_team_id": "344",
    "away_team_id": "2633",
    "home_score": 0,
    "away_score": 0,
    "game_status": "Scheduled",
    "neutral_site": false,
    "home_moneyline": 250,
    "away_moneyline": -310,
    "venue": null,
    "tournament": null,
    "conference_game": false,
    "created_at": "2026-02-04T12:33:51.149638",
    "updated_at": "2026-02-11T12:18:29.162228",
    "id": 13879,
    "prediction_date": "2026-02-11T12:39:50.540595",
    "home_win_prob": 0.208078533411026,
    "away_win_prob": 0.7919214367866516,
    "predicted_winner": "Tennessee",
    "predicted_home_win": 0,
    "confidence": 0.7919214367866516,
    "model_name": "AdaptivePredictor",
    "model_version": "ad6af36",
    "config_version": "7dd58a0bb0e2",
    "commit_hash": "9d65895",
    "source": "live",
    "explanation": "Tennessee is confidently favored: they are significantly stronger overall, they have a vastly superior defense, and they have a major offensive advantage."
  },
  {
    "game_id": "401808228",
    "date": "2026-02-11",
    "season": "2025-26",
    "home_team": "Texas A&M",
    "away_team": "Missouri",
    "home_team_id": "245",
    "away_team_id": "142",
    "home_score": 0,
    "away_score": 0,
    "game_status": "Scheduled",
    "neutral_site": false,
    "home_moneyline": -305,
    "away_moneyline": 245,
    "venue": null,
    "tournament": null,
    "conference_game": false,
    "created_at": "2026-02-04T12:33:51.166832",
    "updated_at": "2026-02-11T12:18:29.162228",
    "id": 13884,
    "prediction_date": "2026-02-11T12:39:50.540630",
    "home_win_prob": 0.8948037028312683,
    "away_win_prob": 0.10519631952047348,
    "predicted_winner": "Texas A&M",
    "predicted_home_win": 1,
    "confidence": 0.8500000238418579,
    "model_name": "AdaptivePredictor",
    "model_version": "ad6af36",
    "config_version": "7dd58a0bb0e2",
    "commit_hash": "9d65895",
    "source": "live",
    "explanation": "Texas A&M is strongly favored: they are significantly stronger overall, they have a vastly superior defense, and they have a major offensive advantage."
  },
  {
    "game_id": "401804924",
    "date": "2026-02-11",
    "season": "2025-26",
    "home_team": "New Mexico State",
    "away_team": "Liberty",
    "home_team_id": "166",
    "away_team_id": "2335",
    "home_score": 0,
    "away_score": 0,
    "game_status": "Scheduled",
    "neutral_site": false,
    "home_moneyline": 140,
    "away_moneyline": -166,
    "venue": null,
    "tournament": null,
    "conference_game": false,
    "created_at": "2026-02-04T12:33:51.170232",
    "updated_at": "2026-02-11T12:18:29.162228",
    "id": 13885,
    "prediction_date": "2026-02-11T12:39:50.540665",
    "home_win_prob": 0.014810717664659023,
    "away_win_prob": 0.9851892590522766,
    "predicted_winner": "Liberty",
    "predicted_home_win": 0,
    "confidence": 0.8500000238418579,
    "model_name": "AdaptivePredictor",
    "model_version": "ad6af36",
    "config_version": "7dd58a0bb0e2",
    "commit_hash": "9d65895",
    "source": "live",
    "explanation": "Liberty is strongly favored: they are significantly stronger overall, they have a vastly superior defense, and they have a major offensive advantage."
  },
  {
    "game_id": "401829242",
    "date": "2026-02-11",
    "season": "2025-26",
    "home_team": "San Diego Toreros",
    "away_team": "Portland",
    "home_team_id": "301",
    "away_team_id": "2501",
    "home_score": 0,
    "away_score": 0,
    "game_status": "Scheduled",
    "neutral_site": false,
    "home_moneyline": -135,
    "away_moneyline": 114,
    "venue": null,
    "tournament": null,
    "conference_game": false,
    "created_at": "2026-02-04T12:33:51.173467",
    "updated_at": "2026-02-11T12:18:29.162228",
    "id": 13886,
    "prediction_date": "2026-02-11T12:39:50.540700",
    "home_win_prob": 0.6401592493057251,
    "away_win_prob": 0.3598407804965973,
    "predicted_winner": "San Diego Toreros",
    "predicted_home_win": 1,
    "confidence": 0.6401592493057251,
    "model_name": "AdaptivePredictor",
    "model_version": "ad6af36",
    "config_version": "7dd58a0bb0e2",
    "commit_hash": "9d65895",
    "source": "live",
    "explanation": "San Diego Toreros is narrowly favored: they are dominant at their home venue, they have faced much tougher competition, and they are significantly stronger overall."
  },
  {
    "game_id": "401829243",
    "date": "2026-02-11",
    "season": "2025-26",
    "home_team": "Santa Clara",
    "away_team": "Seattle U",
    "home_team_id": "2541",
    "away_team_id": "2547",
    "home_score": 0,
    "away_score": 0,
    "game_status": "Scheduled",
    "neutral_site": false,
    "home_moneyline": -1350,
    "away_moneyline": 800,
    "venue": null,
    "tournament": null,
    "conference_game": false,
    "created_at": "2026-02-04T12:33:51.176892",
    "updated_at": "2026-02-11T12:18:29.162228",
    "id": 13887,
    "prediction_date": "2026-02-11T12:39:50.540735",
    "home_win_prob": 0.8948037028312683,
    "away_win_prob": 0.10519631952047348,
    "predicted_winner": "Santa Clara",
    "predicted_home_win": 1,
    "confidence": 0.8500000238418579,
    "model_name": "AdaptivePredictor",
    "model_version": "ad6af36",
    "config_version": "7dd58a0bb0e2",
    "commit_hash": "9d65895",
    "source": "live",
    "explanation": "Santa Clara is strongly favored: they are significantly stronger overall, they have a vastly superior defense, and they have a major offensive advantage."
  },
  {
    "game_id": "401829241",
    "date": "2026-02-11",
    "season": "2025-26",
    "home_team": "Saint Mary's",
    "away_team": "Pepperdine",
    "home_team_id": "2608",
    "away_team_id": "2492",
    "home_score": 0,
    "away_score": 0,
    "game_status": "Scheduled",
    "neutral_site": false,
    "home_moneyline": -10000,
    "away_moneyline": 3000,
    "venue": null,
    "tournament": null,
    "conference_game": false,
    "created_at": "2026-02-04T12:33:51.180068",
    "updated_at": "2026-02-11T12:18:29.162228",
    "id": 13888,
    "prediction_date": "2026-02-11T12:39:50.540771",
    "home_win_prob": 0.9900000095367432,
    "away_win_prob": 0.009999999776482582,
    "predicted_winner": "Saint Mary's",
    "predicted_home_win": 1,
    "confidence": 0.8500000238418579,
    "model_name": "AdaptivePredictor",
    "model_version": "ad6af36",
    "config_version": "7dd58a0bb0e2",
    "commit_hash": "9d65895",
    "source": "live",
    "explanation": "Saint Mary's is strongly favored: they are significantly stronger overall, they have a vastly superior defense, and they have a major offensive advantage."
  },
  {
    "game_id": "401829239",
    "date": "2026-02-11",
    "season": "2025-26",
    "home_team": "Pacific",
    "away_team": "Loyola Marymount",
    "home_team_id": "279",
    "away_team_id": "2351",
    "home_score": 0,
    "away_score": 0,
    "game_status": "Scheduled",
    "neutral_site": false,
    "home_moneyline": -250,
    "away_moneyline": 205,
    "venue": null,
    "tournament": null,
    "conference_game": false,
    "created_at": "2026-02-04T12:33:51.183552",
    "updated_at": "2026-02-11T12:18:29.162228",
    "id": 13889,
    "prediction_date": "2026-02-11T12:39:50.540806",
    "home_win_prob": 0.9900000095367432,
    "away_win_prob": 0.009999999776482582,
    "predicted_winner": "Pacific",
    "predicted_home_win": 1,
    "confidence": 0.8500000238418579,
    "model_name": "AdaptivePredictor",
    "model_version": "ad6af36",
    "config_version": "7dd58a0bb0e2",
    "commit_hash": "9d65895",
    "source": "live",
    "explanation": "Pacific is strongly favored: they are significantly stronger overall, they have a vastly superior defense, and they have a major offensive advantage."
  },
  {
    "game_id": "401823801",
    "date": "2026-02-11",
    "season": "2025-26",
    "home_team": "Grand Canyon Lopes",
    "away_team": "New Mexico",
    "home_team_id": "2253",
    "away_team_id": "167",
    "home_score": 0,
    "away_score": 0,
    "game_status": "Scheduled",
    "neutral_site": false,
    "home_moneyline": -122,
    "away_moneyline": 102,
    "venue": null,
    "tournament": null,
    "conference_game": false,
    "created_at": "2026-02-04T12:33:51.187011",
    "updated_at": "2026-02-11T12:18:29.162228",
    "id": 13890,
    "prediction_date": "2026-02-11T12:39:50.540841",
    "home_win_prob": 0.40433648228645325,
    "away_win_prob": 0.5956635475158691,
    "predicted_winner": "New Mexico",
    "predicted_home_win": 0,
    "confidence": 0.5956635475158691,
    "model_name": "AdaptivePredictor",
    "model_version": "ad6af36",
    "config_version": "7dd58a0bb0e2",
    "commit_hash": "9d65895",
    "source": "live",
    "explanation": "New Mexico is narrowly favored: they are significantly stronger overall, they have a vastly superior defense, and they have a major offensive advantage."
  },
  {
    "game_id": "401814559",
    "date": "2026-02-11",
    "season": "2025-26",
    "home_team": "Ball State",
    "away_team": "Buffalo",
    "home_team_id": "2050",
    "away_team_id": "2084",
    "home_score": 0,
    "away_score": 0,
    "game_status": "Scheduled",
    "neutral_site": false,
    "home_moneyline": null,
    "away_moneyline": -120,
    "venue": null,
    "tournament": null,
    "conference_game": false,
    "created_at": "2026-02-04T12:33:51.056466",
    "updated_at": "2026-02-11T12:18:29.162228",
    "id": 13852,
    "prediction_date": "2026-02-11T12:39:50.539472",
    "home_win_prob": 0.11472060531377792,
    "away_win_prob": 0.8852794170379639,
    "predicted_winner": "Buffalo",
    "predicted_home_win": 0,
    "confidence": 0.8500000238418579,
    "model_name": "AdaptivePredictor",
    "model_version": "ad6af36",
    "config_version": "7dd58a0bb0e2",
    "commit_hash": "9d65895",
    "source": "live",
    "explanation": "Buffalo is strongly favored: they have faced much tougher competition and they have a slight home court advantage."
  }
]