[
  {
    "team_id": "UConn",
    "display_name": "UConn",
    "conference": null,
    "predictions_made": 18,
    "correct_predictions": 18,
    "prediction_accuracy": 1.0,
    "avg_confidence": 0.816235813829634,
    "team_wins": 22,
    "team_losses": 1
  },
  {
    "team_id": "Saint Louis",
    "display_name": "Saint Louis",
    "conference": null,
    "predictions_made": 17,
    "correct_predictions": 17,
    "prediction_accuracy": 1.0,
    "avg_confidence": 0.8325286858222064,
    "team_wins": 22,
    "team_losses": 1
  },
  {
    "team_id": "Miami (OH)",
    "display_name": "Miami (OH)",
    "conference": null,
    "predictions_made": 15,
    "correct_predictions": 15,
    "prediction_accuracy": 1.0,
    "avg_confidence": 0.7719168504079182,
    "team_wins": 23,
    "team_losses": 0
  },
  {
    "team_id": "Duke",
    "display_name": "Duke",
    "conference": null,
    "predictions_made": 15,
    "correct_predictions": 15,
    "prediction_accuracy": 1.0,
    "avg_confidence": 0.8077318747838338,
    "team_wins": 21,
    "team_losses": 1
  },
  {
    "team_id": "Navy",
    "display_name": "Navy",
    "conference": null,
    "predictions_made": 14,
    "correct_predictions": 14,
    "prediction_accuracy": 1.0,
    "avg_confidence": 0.8423541486263275,
    "team_wins": 18,
    "team_losses": 6
  },
  {
    "team_id": "Akron",
    "display_name": "Akron",
    "conference": null,
    "predictions_made": 14,
    "correct_predictions": 14,
    "prediction_accuracy": 1.0,
    "avg_confidence": 0.8274978271552494,
    "team_wins": 19,
    "team_losses": 4
  },
  {
    "team_id": "Arizona",
    "display_name": "Arizona",
    "conference": null,
    "predictions_made": 14,
    "correct_predictions": 14,
    "prediction_accuracy": 1.0,
    "avg_confidence": 0.8085805560861316,
    "team_wins": 22,
    "team_losses": 0
  },
  {
    "team_id": "Liberty",
    "display_name": "Liberty",
    "conference": null,
    "predictions_made": 12,
    "correct_predictions": 12,
    "prediction_accuracy": 1.0,
    "avg_confidence": 0.8230078816413879,
    "team_wins": 19,
    "team_losses": 3
  },
  {
    "team_id": "Portland State",
    "display_name": "Portland State",
    "conference": null,
    "predictions_made": 10,
    "correct_predictions": 10,
    "prediction_accuracy": 1.0,
    "avg_confidence": 0.7806179523468018,
    "team_wins": 15,
    "team_losses": 6
  },
  {
    "team_id": "South Carolina Gamecocks",
    "display_name": "South Carolina Gamecocks",
    "conference": null,
    "predictions_made": 7,
    "correct_predictions": 7,
    "prediction_accuracy": 1.0,
    "avg_confidence": 0.7683721440179008,
    "team_wins": 11,
    "team_losses": 12
  },
  {
    "team_id": "North Carolina Central",
    "display_name": "North Carolina Central",
    "conference": null,
    "predictions_made": 6,
    "correct_predictions": 6,
    "prediction_accuracy": 1.0,
    "avg_confidence": 0.7250794470310211,
    "team_wins": 8,
    "team_losses": 12
  },
  {
    "team_id": "Western Michigan",
    "display_name": "Western Michigan",
    "conference": null,
    "predictions_made": 6,
    "correct_predictions": 6,
    "prediction_accuracy": 1.0,
    "avg_confidence": 0.7814879715442657,
    "team_wins": 8,
    "team_losses": 14
  },
  {
    "team_id": "Gonzaga",
    "display_name": "Gonzaga",
    "conference": null,
    "predictions_made": 19,
    "correct_predictions": 18,
    "prediction_accuracy": 0.9473684430122375,
    "avg_confidence": 0.8269722963634291,
    "team_wins": 22,
    "team_losses": 2
  },
  {
    "team_id": "Houston",
    "display_name": "Houston",
    "conference": null,
    "predictions_made": 15,
    "correct_predictions": 14,
    "prediction_accuracy": 0.9333333373069763,
    "avg_confidence": 0.8171335140864054,
    "team_wins": 20,
    "team_losses": 2
  },
  {
    "team_id": "Michigan State",
    "display_name": "Michigan State",
    "conference": null,
    "predictions_made": 15,
    "correct_predictions": 14,
    "prediction_accuracy": 0.9333333373069763,
    "avg_confidence": 0.787466303507487,
    "team_wins": 19,
    "team_losses": 4
  },
  {
    "team_id": "Stephen F. Austin",
    "display_name": "Stephen F. Austin",
    "conference": null,
    "predictions_made": 15,
    "correct_predictions": 14,
    "prediction_accuracy": 0.9333333373069763,
    "avg_confidence": 0.8032530784606934,
    "team_wins": 20,
    "team_losses": 3
  },
  {
    "team_id": "Michigan",
    "display_name": "Michigan",
    "conference": null,
    "predictions_made": 15,
    "correct_predictions": 14,
    "prediction_accuracy": 0.9333333373069763,
    "avg_confidence": 0.8163309057553609,
    "team_wins": 21,
    "team_losses": 1
  },
  {
    "team_id": "McNeese",
    "display_name": "McNeese",
    "conference": null,
    "predictions_made": 14,
    "correct_predictions": 13,
    "prediction_accuracy": 0.9285714030265808,
    "avg_confidence": 0.8049237642969403,
    "team_wins": 18,
    "team_losses": 5
  },
  {
    "team_id": "Virginia",
    "display_name": "Virginia",
    "conference": null,
    "predictions_made": 14,
    "correct_predictions": 13,
    "prediction_accuracy": 0.9285714030265808,
    "avg_confidence": 0.7946344486304692,
    "team_wins": 19,
    "team_losses": 3
  },
  {
    "team_id": "Purdue",
    "display_name": "Purdue",
    "conference": null,
    "predictions_made": 13,
    "correct_predictions": 12,
    "prediction_accuracy": 0.9230769276618958,
    "avg_confidence": 0.7725310738270099,
    "team_wins": 18,
    "team_losses": 4
  },
  {
    "team_id": "Oklahoma State",
    "display_name": "Oklahoma State",
    "conference": null,
    "predictions_made": 13,
    "correct_predictions": 12,
    "prediction_accuracy": 0.9230769276618958,
    "avg_confidence": 0.7599100929040176,
    "team_wins": 16,
    "team_losses": 6
  },
  {
    "team_id": "Lipscomb",
    "display_name": "Lipscomb",
    "conference": null,
    "predictions_made": 13,
    "correct_predictions": 12,
    "prediction_accuracy": 0.9230769276618958,
    "avg_confidence": 0.8351339010091928,
    "team_wins": 15,
    "team_losses": 9
  },
  {
    "team_id": "Kansas",
    "display_name": "Kansas",
    "conference": null,
    "predictions_made": 12,
    "correct_predictions": 11,
    "prediction_accuracy": 0.9166666865348816,
    "avg_confidence": 0.7280009786287943,
    "team_wins": 17,
    "team_losses": 5
  },
  {
    "team_id": "Austin Peay Governors",
    "display_name": "Austin Peay Governors",
    "conference": null,
    "predictions_made": 12,
    "correct_predictions": 11,
    "prediction_accuracy": 0.9166666865348816,
    "avg_confidence": 0.7993802676598231,
    "team_wins": 16,
    "team_losses": 6
  },
  {
    "team_id": "South Dakota",
    "display_name": "South Dakota",
    "conference": null,
    "predictions_made": 11,
    "correct_predictions": 10,
    "prediction_accuracy": 0.9090909361839294,
    "avg_confidence": 0.8064842224121094,
    "team_wins": 13,
    "team_losses": 12
  },
  {
    "team_id": "Long Island University",
    "display_name": "Long Island University",
    "conference": null,
    "predictions_made": 10,
    "correct_predictions": 9,
    "prediction_accuracy": 0.8999999761581421,
    "avg_confidence": 0.7553887963294983,
    "team_wins": 15,
    "team_losses": 8
  },
  {
    "team_id": "Wyoming",
    "display_name": "Wyoming",
    "conference": null,
    "predictions_made": 9,
    "correct_predictions": 8,
    "prediction_accuracy": 0.8888888955116272,
    "avg_confidence": 0.7844436036215888,
    "team_wins": 13,
    "team_losses": 10
  },
  {
    "team_id": "Grand Canyon Lopes",
    "display_name": "Grand Canyon Lopes",
    "conference": null,
    "predictions_made": 9,
    "correct_predictions": 8,
    "prediction_accuracy": 0.8888888955116272,
    "avg_confidence": 0.7474182446797689,
    "team_wins": 15,
    "team_losses": 7
  },
  {
    "team_id": "Duquesne",
    "display_name": "Duquesne",
    "conference": null,
    "predictions_made": 9,
    "correct_predictions": 8,
    "prediction_accuracy": 0.8888888955116272,
    "avg_confidence": 0.8039161298010085,
    "team_wins": 13,
    "team_losses": 10
  },
  {
    "team_id": "Davidson",
    "display_name": "Davidson",
    "conference": null,
    "predictions_made": 9,
    "correct_predictions": 8,
    "prediction_accuracy": 0.8888888955116272,
    "avg_confidence": 0.8140139116181268,
    "team_wins": 13,
    "team_losses": 9
  },
  {
    "team_id": "Mercer",
    "display_name": "Mercer",
    "conference": null,
    "predictions_made": 9,
    "correct_predictions": 8,
    "prediction_accuracy": 0.8888888955116272,
    "avg_confidence": 0.7909228934182061,
    "team_wins": 15,
    "team_losses": 9
  },
  {
    "team_id": "UNC Asheville",
    "display_name": "UNC Asheville",
    "conference": null,
    "predictions_made": 9,
    "correct_predictions": 8,
    "prediction_accuracy": 0.8888888955116272,
    "avg_confidence": 0.7803685731357999,
    "team_wins": 11,
    "team_losses": 13
  },
  {
    "team_id": "North Carolina",
    "display_name": "North Carolina",
    "conference": null,
    "predictions_made": 17,
    "correct_predictions": 15,
    "prediction_accuracy": 0.8823529481887817,
    "avg_confidence": 0.822202230201048,
    "team_wins": 18,
    "team_losses": 4
  },
  {
    "team_id": "Saint Mary's",
    "display_name": "Saint Mary's",
    "conference": null,
    "predictions_made": 17,
    "correct_predictions": 15,
    "prediction_accuracy": 0.8823529481887817,
    "avg_confidence": 0.8233149612651152,
    "team_wins": 20,
    "team_losses": 4
  },
  {
    "team_id": "Iowa State",
    "display_name": "Iowa State",
    "conference": null,
    "predictions_made": 17,
    "correct_predictions": 15,
    "prediction_accuracy": 0.8823529481887817,
    "avg_confidence": 0.7847943165723015,
    "team_wins": 20,
    "team_losses": 2
  },
  {
    "team_id": "UCF",
    "display_name": "UCF",
    "conference": null,
    "predictions_made": 16,
    "correct_predictions": 14,
    "prediction_accuracy": 0.875,
    "avg_confidence": 0.7499393410980701,
    "team_wins": 17,
    "team_losses": 5
  },
  {
    "team_id": "Tulsa Golden Hurricane",
    "display_name": "Tulsa Golden Hurricane",
    "conference": null,
    "predictions_made": 16,
    "correct_predictions": 14,
    "prediction_accuracy": 0.875,
    "avg_confidence": 0.792911771684885,
    "team_wins": 20,
    "team_losses": 3
  },
  {
    "team_id": "North Dakota State",
    "display_name": "North Dakota State",
    "conference": null,
    "predictions_made": 16,
    "correct_predictions": 14,
    "prediction_accuracy": 0.875,
    "avg_confidence": 0.811941884458065,
    "team_wins": 19,
    "team_losses": 6
  },
  {
    "team_id": "St. John's",
    "display_name": "St. John's",
    "conference": null,
    "predictions_made": 16,
    "correct_predictions": 14,
    "prediction_accuracy": 0.875,
    "avg_confidence": 0.7836543805897236,
    "team_wins": 17,
    "team_losses": 5
  },
  {
    "team_id": "Texas Tech",
    "display_name": "Texas Tech",
    "conference": null,
    "predictions_made": 16,
    "correct_predictions": 14,
    "prediction_accuracy": 0.875,
    "avg_confidence": 0.780970674008131,
    "team_wins": 16,
    "team_losses": 6
  },
  {
    "team_id": "UT Martin",
    "display_name": "UT Martin",
    "conference": null,
    "predictions_made": 16,
    "correct_predictions": 14,
    "prediction_accuracy": 0.875,
    "avg_confidence": 0.7835558876395226,
    "team_wins": 19,
    "team_losses": 5
  },
  {
    "team_id": "Kansas State",
    "display_name": "Kansas State",
    "conference": null,
    "predictions_made": 8,
    "correct_predictions": 7,
    "prediction_accuracy": 0.875,
    "avg_confidence": 0.7287992015480995,
    "team_wins": 10,
    "team_losses": 12
  },
  {
    "team_id": "Texas Longhorns",
    "display_name": "Texas Longhorns",
    "conference": null,
    "predictions_made": 8,
    "correct_predictions": 7,
    "prediction_accuracy": 0.875,
    "avg_confidence": 0.7737971916794777,
    "team_wins": 14,
    "team_losses": 9
  },
  {
    "team_id": "Utah Valley",
    "display_name": "Utah Valley",
    "conference": null,
    "predictions_made": 15,
    "correct_predictions": 13,
    "prediction_accuracy": 0.8666666746139526,
    "avg_confidence": 0.7766950170199076,
    "team_wins": 17,
    "team_losses": 6
  },
  {
    "team_id": "New Mexico",
    "display_name": "New Mexico",
    "conference": null,
    "predictions_made": 15,
    "correct_predictions": 13,
    "prediction_accuracy": 0.8666666746139526,
    "avg_confidence": 0.804636545976003,
    "team_wins": 18,
    "team_losses": 5
  },
  {
    "team_id": "Villanova",
    "display_name": "Villanova",
    "conference": null,
    "predictions_made": 15,
    "correct_predictions": 13,
    "prediction_accuracy": 0.8666666746139526,
    "avg_confidence": 0.7907312472661336,
    "team_wins": 17,
    "team_losses": 5
  },
  {
    "team_id": "Texas A&M",
    "display_name": "Texas A&M",
    "conference": null,
    "predictions_made": 14,
    "correct_predictions": 12,
    "prediction_accuracy": 0.8571428656578064,
    "avg_confidence": 0.8168104631560189,
    "team_wins": 17,
    "team_losses": 5
  },
  {
    "team_id": "UNC Wilmington Seahawks",
    "display_name": "UNC Wilmington Seahawks",
    "conference": null,
    "predictions_made": 14,
    "correct_predictions": 12,
    "prediction_accuracy": 0.8571428656578064,
    "avg_confidence": 0.8066283932753971,
    "team_wins": 19,
    "team_losses": 4
  },
  {
    "team_id": "Miami (FL)",
    "display_name": "Miami (FL)",
    "conference": null,
    "predictions_made": 14,
    "correct_predictions": 12,
    "prediction_accuracy": 0.8571428656578064,
    "avg_confidence": 0.8080543960843768,
    "team_wins": 17,
    "team_losses": 5
  },
  {
    "team_id": "Saint Joseph's",
    "display_name": "Saint Joseph's",
    "conference": null,
    "predictions_made": 7,
    "correct_predictions": 6,
    "prediction_accuracy": 0.8571428656578064,
    "avg_confidence": 0.7730933342661176,
    "team_wins": 15,
    "team_losses": 8
  }
]