[
  {
    "id": 292,
    "game_id": "401825524",
    "prediction_id": 14152,
    "bet_team": "Michigan",
    "bet_amount": 10.0,
    "moneyline": -162,
    "confidence": 0.8500000238418579,
    "value_score": 0.25484734773635864,
    "bet_won": null,
    "actual_winner": null,
    "payout": 0.0,
    "profit": null,
    "bet_type": "moneyline",
    "strategy": "value_betting",
    "created_at": "2026-02-17T12:36:47.903940",
    "settled_at": null,
    "game_date": "2026-02-17",
    "home_team": "Purdue",
    "away_team": "Michigan",
    "home_moneyline": 136,
    "away_moneyline": -162,
    "explanation": "Michigan is strongly favored: they are significantly stronger overall, they have a major offensive advantage, and they have a vastly superior defense."
  },
  {
    "id": 293,
    "game_id": "401814572",
    "prediction_id": 14159,
    "bet_team": "Miami (OH)",
    "bet_amount": 10.0,
    "moneyline": -166,
    "confidence": 0.8500000238418579,
    "value_score": 0.24853385984897614,
    "bet_won": null,
    "actual_winner": null,
    "payout": 0.0,
    "profit": null,
    "bet_type": "moneyline",
    "strategy": "value_betting",
    "created_at": "2026-02-17T12:36:47.906214",
    "settled_at": null,
    "game_date": "2026-02-17",
    "home_team": "Massachusetts",
    "away_team": "Miami (OH)",
    "home_moneyline": 140,
    "away_moneyline": -166,
    "explanation": "Miami (OH) is strongly favored: they are significantly stronger overall, they have faced much tougher competition, and they have a major offensive advantage."
  },
  {
    "id": 220,
    "game_id": "401830280",
    "prediction_id": 13108,
    "bet_team": "Southern Illinois",
    "bet_amount": 10.0,
    "moneyline": -180,
    "confidence": 0.8500000238418579,
    "value_score": 0.22785717248916626,
    "bet_won": null,
    "actual_winner": null,
    "payout": 0.0,
    "profit": null,
    "bet_type": "moneyline",
    "strategy": "value_betting",
    "created_at": "2026-01-25T12:29:22.929493",
    "settled_at": null,
    "game_date": "2026-01-25",
    "home_team": "Evansville Purple Aces",
    "away_team": "Southern Illinois",
    "home_moneyline": null,
    "away_moneyline": null,
    "explanation": "Southern Illinois is strongly favored: they are significantly stronger overall, they have a major offensive advantage, and they have a vastly superior defense."
  },
  {
    "id": 294,
    "game_id": "401814570",
    "prediction_id": 14155,
    "bet_team": "Eastern Michigan",
    "bet_amount": 10.0,
    "moneyline": -225,
    "confidence": 0.8500000238418579,
    "value_score": 0.17346157133579254,
    "bet_won": null,
    "actual_winner": null,
    "payout": 0.0,
    "profit": null,
    "bet_type": "moneyline",
    "strategy": "value_betting",
    "created_at": "2026-02-17T12:36:47.908121",
    "settled_at": null,
    "game_date": "2026-02-17",
    "home_team": "Eastern Michigan",
    "away_team": "Central Michigan",
    "home_moneyline": -225,
    "away_moneyline": 185,
    "explanation": "Eastern Michigan is strongly favored: they are significantly stronger overall, they are dominant at their home venue, and they have a vastly superior defense."
  }
]